Workbook

Sheet Instructions
A1: AI Maturity Assessment — v1
A3: How to use this assessment
A5: 1. Fill in the Respondent Info tab with your name, role, organization, and date.
A6: 2. Open the Survey tab. For each question, select the response that best describes your organization from the dropdown in the Response column.
A7: 3. Use the Evidence / Notes column (column P) to capture supporting documentation, examples, or context.
A8: 4. Leave a row blank if you are not ready to answer — the assessment will exclude it from scoring automatically.
A9: 5. The Dashboard, Gap Analysis, and Recommendations Output tabs update automatically as you select responses.
A11: About the response options
A12: • Each question offers 5 maturity-coded statements. Select the one that most accurately reflects your organization today — not your aspiration.
A13: • If you are unsure about a question, choose "Not sure" — this flags an awareness gap without affecting your maturity score.
A14: • If a question genuinely does not apply to your organization, choose "Not applicable" — same treatment, different flag.

Sheet Respondent Info
A1: AI Maturity Assessment — Respondent Information
A3: Respondent Name
A4: Role / Title
A5: Function / Department
A6: Date Completed
A7: Organization
A8: Engagement / Project Reference
A9: Notes

Sheet Survey
A1: Question ID | B1: Domain | C1: Subsection | D1: Capability | E1: Question Type | F1: Primary Audience | G1: Secondary Audience | H1: Response Type | I1: Question | J1: Response | K1: Hidden Score | L1: Score Treatment | M1: Gap Flag | N1: Recommendation ID | O1: Evidence Required | P1: Evidence / Notes | Q1: NIST AI RMF Mapping | R1: ISO 42001 Mapping
A2: GOV-001 | B2: AI Council Governance and Framework Charter | C2: The AI Council (Structure & Authority) | D2: AI Executive Accountability | E2: Capability | F2: Executive | G2: Governance/Risk/Compliance | H2: Single-select dropdown | I2: Which best describes executive accountability for AI in your organization? | J2: A named executive owns enterprise AI strategy, governance, funding, and prioritization | K2: =IFERROR(_xlfn.XLOOKUP($A2&"|"&$J2,'Response Mapping'!$C$2:$C$1086,'Response Mapping'!$D$2:$D$1086),"") -> 4 | L2: =IFERROR(_xlfn.XLOOKUP($A2&"|"&$J2,'Response Mapping'!$C$2:$C$1086,'Response Mapping'!$E$2:$E$1086),"") -> Include | M2: =IFERROR(_xlfn.XLOOKUP($A2&"|"&$J2,'Response Mapping'!$C$2:$C$1086,'Response Mapping'!$F$2:$F$1086),"") -> Mature Capability | N2: =IFERROR(_xlfn.XLOOKUP($A2&"|"&$J2,'Response Mapping'!$C$2:$C$1086,'Response Mapping'!$G$2:$G$1086),"") -> REC-GOV-001-L4 | O2: =IF($K2="","",IF($K2>=4,"Yes","No")) -> Yes | Q2: Govern | R2: Clause 5 (Leadership)
A3: GOV-002 | B3: AI Council Governance and Framework Charter | C3: The AI Council (Structure & Authority) | D3: Cross-Functional AI Governance | E3: Capability | F3: Governance/Risk/Compliance | G3: Executive | H3: Single-select dropdown | I3: Which best describes the cross-functional representation of your AI governance council or equivalent decision-making body? | J3: The governance body includes consistent representation from IT, business units, legal, security/risk, HR, and data/analytics, with defined roles and decision rights | K3: =IFERROR(_xlfn.XLOOKUP($A3&"|"&$J3,'Response Mapping'!$C$2:$C$1086,'Response Mapping'!$D$2:$D$1086),"") -> 4 | L3: =IFERROR(_xlfn.XLOOKUP($A3&"|"&$J3,'Response Mapping'!$C$2:$C$1086,'Response Mapping'!$E$2:$E$1086),"") -> Include | M3: =IFERROR(_xlfn.XLOOKUP($A3&"|"&$J3,'Response Mapping'!$C$2:$C$1086,'Response Mapping'!$F$2:$F$1086),"") -> Mature Capability | N3: =IFERROR(_xlfn.XLOOKUP($A3&"|"&$J3,'Response Mapping'!$C$2:$C$1086,'Response Mapping'!$G$2:$G$1086),"") -> REC-GOV-002-L4 | O3: =IF($K3="","",IF($K3>=4,"Yes","No")) -> Yes | Q3: Govern | R3: Clause 5 (Leadership)
A4: GOV-003 | B4: AI Council Governance and Framework Charter | C4: The AI Council (Structure & Authority) | D4: Governance Authority and Decision Rights | E4: Capability | F4: Governance/Risk/Compliance | G4: Executive | H4: Single-select dropdown | I4: Which best describes the authority of your AI governance council to approve, pause, or stop AI initiatives based on risk? | J4: The council can review AI initiatives, but its authority to enforce decisions is unclear or inconsistently applied | K4: =IFERROR(_xlfn.XLOOKUP($A4&"|"&$J4,'Response Mapping'!$C$2:$C$1086,'Response Mapping'!$D$2:$D$1086),"") -> 3 | L4: =IFERROR(_xlfn.XLOOKUP($A4&"|"&$J4,'Response Mapping'!$C$2:$C$1086,'Response Mapping'!$E$2:$E$1086),"") -> Include | M4: =IFERROR(_xlfn.XLOOKUP($A4&"|"&$J4,'Response Mapping'!$C$2:$C$1086,'Response Mapping'!$F$2:$F$1086),"") -> Partial Capability | N4: =IFERROR(_xlfn.XLOOKUP($A4&"|"&$J4,'Response Mapping'!$C$2:$C$1086,'Response Mapping'!$G$2:$G$1086),"") -> REC-GOV-003-L3 | O4: =IF($K4="","",IF($K4>=4,"Yes","No")) -> No | Q4: Govern | R4: Clause 6 (Planning)
A5: GOV-004 | B5: AI Council Governance and Framework Charter | C5: The AI Council (Structure & Authority) | D5: Governance Cadence and Responsiveness | E5: Capability | F5: Governance/Risk/Compliance | G5: Executive | H5: Single-select dropdown | I5: Which best describes the meeting cadence and responsiveness of your AI governance council or review process? | J5: The council meets periodically, but the cadence is not always sufficient to support timely AI review and approval | K5: =IFERROR(_xlfn.XLOOKUP($A5&"|"&$J5,'Response Mapping'!$C$2:$C$1086,'Response Mapping'!$D$2:$D$1086),"") -> 3 | L5: =IFERROR(_xlfn.XLOOKUP($A5&"|"&$J5,'Response Mapping'!$C$2:$C$1086,'Response Mapping'!$E$2:$E$1086),"") -> Include | M5: =IFERROR(_xlfn.XLOOKUP($A5&"|"&$J5,'Response Mapping'!$C$2:$C$1086,'Response Mapping'!$F$2:$F$1086),"") -> Partial Capability | N5: =IFERROR(_xlfn.XLOOKUP($A5&"|"&$J5,'Response Mapping'!$C$2:$C$1086,'Response Mapping'!$G$2:$G$1086),"") -> REC-GOV-004-L3 | O5: =IF($K5="","",IF($K5>=4,"Yes","No")) -> No | Q5: Govern | R5: Clause 9 (Performance Evaluation)
A6: GOV-005 | B6: AI Council Governance and Framework Charter | C6: The AI Council (Structure & Authority) | D6: AI Risk Escalation and Tie-Breaking | E6: Capability | F6: Governance/Risk/Compliance | G6: Executive | H6: Single-select dropdown | I6: Which best describes how AI risk disagreements are escalated and resolved? | J6: Disagreements are handled informally between teams, with no documented tie-breaking authority | K6: =IFERROR(_xlfn.XLOOKUP($A6&"|"&$J6,'Response Mapping'!$C$2:$C$1086,'Response Mapping'!$D$2:$D$1086),"") -> 2 | L6: =IFERROR(_xlfn.XLOOKUP($A6&"|"&$J6,'Response Mapping'!$C$2:$C$1086,'Response Mapping'!$E$2:$E$1086),"") -> Include | M6: =IFERROR(_xlfn.XLOOKUP($A6&"|"&$J6,'Response Mapping'!$C$2:$C$1086,'Response Mapping'!$F$2:$F$1086),"") -> Informal Governance | N6: =IFERROR(_xlfn.XLOOKUP($A6&"|"&$J6,'Response Mapping'!$C$2:$C$1086,'Response Mapping'!$G$2:$G$1086),"") -> REC-GOV-005-L1 | O6: =IF($K6="","",IF($K6>=4,"Yes","No")) -> No | Q6: Govern | R6: Clause 6 (Planning)
A7: GOV-006 | B7: AI Council Governance and Framework Charter | C7: Governance Framework (Policies & Standards) | D7: AI Risk Classification | E7: Capability | F7: Governance/Risk/Compliance | G7: IT/Architecture | H7: Single-select dropdown | I7: Which best describes your organization's process for classifying AI use cases by risk level? | J7: AI use cases are classified into defined risk tiers, and each tier triggers specific review, approval, documentation, and oversight requirements | K7: =IFERROR(_xlfn.XLOOKUP($A7&"|"&$J7,'Response Mapping'!$C$2:$C$1086,'Response Mapping'!$D$2:$D$1086),"") -> 4 | L7: =IFERROR(_xlfn.XLOOKUP($A7&"|"&$J7,'Response Mapping'!$C$2:$C$1086,'Response Mapping'!$E$2:$E$1086),"") -> Include | M7: =IFERROR(_xlfn.XLOOKUP($A7&"|"&$J7,'Response Mapping'!$C$2:$C$1086,'Response Mapping'!$F$2:$F$1086),"") -> Mature Capability | N7: =IFERROR(_xlfn.XLOOKUP($A7&"|"&$J7,'Response Mapping'!$C$2:$C$1086,'Response Mapping'!$G$2:$G$1086),"") -> REC-GOV-006-L4 | O7: =IF($K7="","",IF($K7>=4,"Yes","No")) -> Yes | Q7: Map | R7: Clause 6.1 (Risk Management)
A8: GOV-007 | B8: AI Council Governance and Framework Charter | C8: Governance Framework (Policies & Standards) | D8: Responsible AI Standards and Metrics | E8: Capability | F8: Governance/Risk/Compliance | G8: Data/Analytics | H8: Single-select dropdown | I8: Which best describes how your organization defines and measures Responsible AI principles such as fairness, transparency, explainability, privacy, and safety? | J8: Responsible AI principles are discussed in general terms, but are not documented or measured | K8: =IFERROR(_xlfn.XLOOKUP($A8&"|"&$J8,'Response Mapping'!$C$2:$C$1086,'Response Mapping'!$D$2:$D$1086),"") -> 2 | L8: =IFERROR(_xlfn.XLOOKUP($A8&"|"&$J8,'Response Mapping'!$C$2:$C$1086,'Response Mapping'!$E$2:$E$1086),"") -> Include | M8: =IFERROR(_xlfn.XLOOKUP($A8&"|"&$J8,'Response Mapping'!$C$2:$C$1086,'Response Mapping'!$F$2:$F$1086),"") -> Principles Without Controls | N8: =IFERROR(_xlfn.XLOOKUP($A8&"|"&$J8,'Response Mapping'!$C$2:$C$1086,'Response Mapping'!$G$2:$G$1086),"") -> REC-GOV-007-L1 | O8: =IF($K8="","",IF($K8>=4,"Yes","No")) -> No | Q8: Measure | R8: Clause 8 (Operation)
A9: GOV-008 | B9: AI Council Governance and Framework Charter | C9: Governance Framework (Policies & Standards) | D9: Shadow AI Management | E9: Capability | F9: Governance/Risk/Compliance | G9: IT/Architecture | H9: Single-select dropdown | I9: Which best describes your organization's policy and controls for employee use of public or unapproved AI tools? | J9: Shadow AI is actively managed through policy, training, approved enterprise tools, monitoring, exception handling, and periodic compliance review | K9: =IFERROR(_xlfn.XLOOKUP($A9&"|"&$J9,'Response Mapping'!$C$2:$C$1086,'Response Mapping'!$D$2:$D$1086),"") -> 5 | L9: =IFERROR(_xlfn.XLOOKUP($A9&"|"&$J9,'Response Mapping'!$C$2:$C$1086,'Response Mapping'!$E$2:$E$1086),"") -> Include | M9: =IFERROR(_xlfn.XLOOKUP($A9&"|"&$J9,'Response Mapping'!$C$2:$C$1086,'Response Mapping'!$F$2:$F$1086),"") -> Optimized Capability | N9: =IFERROR(_xlfn.XLOOKUP($A9&"|"&$J9,'Response Mapping'!$C$2:$C$1086,'Response Mapping'!$G$2:$G$1086),"") -> REC-GOV-008-L5 | O9: =IF($K9="","",IF($K9>=4,"Yes","No")) -> Yes | Q9: Manage | R9: Clause 8.3 (Operational Controls)
A10: GOV-009 | B10: AI Council Governance and Framework Charter | C10: Governance Framework (Policies & Standards) | D10: AI Documentation and Deployment Readiness | E10: Capability | F10: Engineering/Delivery | G10: Governance/Risk/Compliance | H10: Single-select dropdown | I10: Which best describes the documentation required before an AI solution is approved for deployment? | J10: Documentation is created inconsistently and varies by team or project | K10: =IFERROR(_xlfn.XLOOKUP($A10&"|"&$J10,'Response Mapping'!$C$2:$C$1086,'Response Mapping'!$D$2:$D$1086),"") -> 2 | L10: =IFERROR(_xlfn.XLOOKUP($A10&"|"&$J10,'Response Mapping'!$C$2:$C$1086,'Response Mapping'!$E$2:$E$1086),"") -> Include | M10: =IFERROR(_xlfn.XLOOKUP($A10&"|"&$J10,'Response Mapping'!$C$2:$C$1086,'Response Mapping'!$F$2:$F$1086),"") -> Inconsistent Practice | N10: =IFERROR(_xlfn.XLOOKUP($A10&"|"&$J10,'Response Mapping'!$C$2:$C$1086,'Response Mapping'!$G$2:$G$1086),"") -> REC-GOV-009-L1 | O10: =IF($K10="","",IF($K10>=4,"Yes","No")) -> No | Q10: Govern | R10: Clause 7.5 (Documented Information)
A11: GOV-010 | B11: AI Council Governance and Framework Charter | C11: Governance Framework (Policies & Standards) | D11: Regulatory and Standards Alignment | E11: Capability | F11: Governance/Risk/Compliance | G11: Executive | H11: Single-select dropdown | I11: Which best describes how your AI governance framework aligns to current and emerging AI regulations, standards, and risk management frameworks? | J11: Some AI policies or controls reference external frameworks, but coverage is incomplete or inconsistently maintained | K11: =IFERROR(_xlfn.XLOOKUP($A11&"|"&$J11,'Response Mapping'!$C$2:$C$1086,'Response Mapping'!$D$2:$D$1086),"") -> 3 | L11: =IFERROR(_xlfn.XLOOKUP($A11&"|"&$J11,'Response Mapping'!$C$2:$C$1086,'Response Mapping'!$E$2:$E$1086),"") -> Include | M11: =IFERROR(_xlfn.XLOOKUP($A11&"|"&$J11,'Response Mapping'!$C$2:$C$1086,'Response Mapping'!$F$2:$F$1086),"") -> Partial Capability | N11: =IFERROR(_xlfn.XLOOKUP($A11&"|"&$J11,'Response Mapping'!$C$2:$C$1086,'Response Mapping'!$G$2:$G$1086),"") -> REC-GOV-010-L3 | O11: =IF($K11="","",IF($K11>=4,"Yes","No")) -> No | Q11: Govern | R11: Clause 4 (Context of the Organization)
A12: GOV-011 | B12: AI Council Governance and Framework Charter | C12: Operational Gaps (Implementation) | D12: AI Asset Inventory | E12: Capability | F12: Governance/Risk/Compliance | G12: IT/Architecture | H12: Single-select dropdown | I12: Which best describes your organization's ability to inventory and track all AI models and AI-enabled vendor capabilities in use? | J12: A central inventory exists, but it is incomplete, manually maintained, or omits embedded vendor AI capabilities | K12: =IFERROR(_xlfn.XLOOKUP($A12&"|"&$J12,'Response Mapping'!$C$2:$C$1086,'Response Mapping'!$D$2:$D$1086),"") -> 3 | L12: =IFERROR(_xlfn.XLOOKUP($A12&"|"&$J12,'Response Mapping'!$C$2:$C$1086,'Response Mapping'!$E$2:$E$1086),"") -> Include | M12: =IFERROR(_xlfn.XLOOKUP($A12&"|"&$J12,'Response Mapping'!$C$2:$C$1086,'Response Mapping'!$F$2:$F$1086),"") -> Partial Capability | N12: =IFERROR(_xlfn.XLOOKUP($A12&"|"&$J12,'Response Mapping'!$C$2:$C$1086,'Response Mapping'!$G$2:$G$1086),"") -> REC-GOV-011-L3 | O12: =IF($K12="","",IF($K12>=4,"Yes","No")) -> No | Q12: Map | R12: Clause 7.5 (Documented Information)
A13: GOV-012 | B13: AI Council Governance and Framework Charter | C13: Operational Gaps (Implementation) | D13: Third-Party AI Risk | E13: Capability | F13: Governance/Risk/Compliance | G13: IT/Architecture | H13: Single-select dropdown | I13: Which best describes your organization's approach to assessing and managing risk for vendor-supplied AI tools and AI-enabled products? | J13: An AI vendor review exists, but coverage of transparency, training data, audit rights, and model updates is inconsistent | K13: =IFERROR(_xlfn.XLOOKUP($A13&"|"&$J13,'Response Mapping'!$C$2:$C$1086,'Response Mapping'!$D$2:$D$1086),"") -> 3 | L13: =IFERROR(_xlfn.XLOOKUP($A13&"|"&$J13,'Response Mapping'!$C$2:$C$1086,'Response Mapping'!$E$2:$E$1086),"") -> Include | M13: =IFERROR(_xlfn.XLOOKUP($A13&"|"&$J13,'Response Mapping'!$C$2:$C$1086,'Response Mapping'!$F$2:$F$1086),"") -> Partial Capability | N13: =IFERROR(_xlfn.XLOOKUP($A13&"|"&$J13,'Response Mapping'!$C$2:$C$1086,'Response Mapping'!$G$2:$G$1086),"") -> REC-GOV-012-L3 | O13: =IF($K13="","",IF($K13>=4,"Yes","No")) -> No | Q13: Manage | R13: Clause 8.4 (Supplier and Third-Party Controls)
... A156: RAC-015 | B156: RACI Matrix | C156: Communication & Awareness (The "Informed") | D156: Vendor Model Change Awareness | E156: Capability | F156: IT/Architecture | G156: Governance/Risk/Compliance | H156: Single-select dropdown | I156: Which best describes who is informed and responsible when an underlying AI vendor releases an API or model change? | J156: Vendor change awareness is automated, integrated with regression testing, supports rapid response to breaking changes, and feeds vendor risk management | K156: =IFERROR(_xlfn.XLOOKUP($A156&"|"&$J156,'Response Mapping'!$C$2:$C$1086,'Response Mapping'!$D$2:$D$1086),"") -> 5 | L156: =IFERROR(_xlfn.XLOOKUP($A156&"|"&$J156,'Response Mapping'!$C$2:$C$1086,'Response Mapping'!$E$2:$E$1086),"") -> Include | M156: =IFERROR(_xlfn.XLOOKUP($A156&"|"&$J156,'Response Mapping'!$C$2:$C$1086,'Response Mapping'!$F$2:$F$1086),"") -> Optimized Capability | N156: =IFERROR(_xlfn.XLOOKUP($A156&"|"&$J156,'Response Mapping'!$C$2:$C$1086,'Response Mapping'!$G$2:$G$1086),"") -> REC-RAC-015-L5 | O156: =IF($K156="","",IF($K156>=4,"Yes","No")) -> Yes | Q156: Manage | R156: Clause 8.4 (Supplier and Third-Party Controls)

Sheet Response Mapping
A1: Question ID | B1: Response Option | C1: Lookup Key | D1: Normalized Score | E1: Score Treatment | F1: Gap Flag | G1: Recommendation ID | H1: Evidence Trigger | I1: Dashboard Category
A2: GOV-001 | B2: No clear executive owner exists for AI | C2: GOV-001|No clear executive owner exists for AI | D2: 1 | E2: Include | F2: Governance Gap | G2: REC-GOV-001-L1 | H2: No | I2: AI Council Governance and Framework Charter
A3: GOV-001 | B3: AI accountability is informal or distributed across multiple leaders without a clear decision owner | C3: GOV-001|AI accountability is informal or distributed across multiple leaders without a clear decision owner | D3: 2 | E3: Include | F3: Governance Gap | G3: REC-GOV-001-L1 | H3: No | I3: AI Council Governance and Framework Charter
A4: GOV-001 | B4: A senior leader or function owns AI strategy, but authority, funding, or decision rights are limited | C4: GOV-001|A senior leader or function owns AI strategy, but authority, funding, or decision rights are limited | D4: 3 | E4: Include | F4: Partial Capability | G4: REC-GOV-001-L3 | H4: No | I4: AI Council Governance and Framework Charter
A5: GOV-001 | B5: A named executive owns enterprise AI strategy, governance, funding, and prioritization | C5: GOV-001|A named executive owns enterprise AI strategy, governance, funding, and prioritization | D5: 4 | E5: Include | F5: Mature Capability | G5: REC-GOV-001-L4 | H5: Yes | I5: AI Council Governance and Framework Charter
A6: GOV-001 | B6: A named executive owns AI accountability and is supported by formal governance, KPIs, risk oversight, and enterprise-wide operating model integration | C6: GOV-001|A named executive owns AI accountability and is supported by formal governance, KPIs, risk oversight, and enterprise-wide operating model integration | D6: 5 | E6: Include | F6: Optimized Capability | G6: REC-GOV-001-L5 | H6: Yes | I6: AI Council Governance and Framework Charter
A7: GOV-001 | B7: Not sure | C7: GOV-001|Not sure | E7: Exclude | F7: Awareness Gap | G7: REC-GOV-001-NS | H7: No | I7: AI Council Governance and Framework Charter
A8: GOV-001 | B8: Not applicable | C8: GOV-001|Not applicable | E8: Exclude | F8: Review Required | G8: REC-GOV-001-NA | H8: No | I8: AI Council Governance and Framework Charter
A9: GOV-002 | B9: No AI governance council or equivalent decision-making body exists | C9: GOV-002|No AI governance council or equivalent decision-making body exists | D9: 1 | E9: Include | F9: Governance Gap | G9: REC-GOV-002-L1 | H9: No | I9: AI Council Governance and Framework Charter
A10: GOV-002 | B10: AI governance is primarily IT-led, with limited business, legal, HR, risk, or ethics involvement | C10: GOV-002|AI governance is primarily IT-led, with limited business, legal, HR, risk, or ethics involvement | D10: 2 | E10: Include | F10: Cross-Functional Gap | G10: REC-GOV-002-L1 | H10: No | I10: AI Council Governance and Framework Charter
A11: GOV-002 | B11: The governance body includes some non-technical representation, but participation is inconsistent or decision rights are unclear | C11: GOV-002|The governance body includes some non-technical representation, but participation is inconsistent or decision rights are unclear | D11: 3 | E11: Include | F11: Partial Capability | G11: REC-GOV-002-L3 | H11: No | I11: AI Council Governance and Framework Charter
A12: GOV-002 | B12: The governance body includes consistent representation from IT, business units, legal, security/risk, HR, and data/analytics, with defined roles and decision rights | C12: GOV-002|The governance body includes consistent representation from IT, business units, legal, security/risk, HR, and data/analytics, with defined roles and decision rights | D12: 4 | E12: Include | F12: Mature Capability | G12: REC-GOV-002-L4 | H12: Yes | I12: AI Council Governance and Framework Charter
A13: GOV-002 | B13: The governance body is fully cross-functional, has formal authority, includes technical and non-technical stakeholders, and regularly adjusts membership based on AI portfolio needs | C13: GOV-002|The governance body is fully cross-functional, has formal authority, includes technical and non-technical stakeholders, and regularly adjusts membership based on AI portfolio needs | D13: 5 | E13: Include | F13: Optimized Capability | G13: REC-GOV-002-L5 | H13: Yes | I13: AI Council Governance and Framework Charter
A14: GOV-002 | B14: Not sure | C14: GOV-002|Not sure | E14: Exclude | F14: Awareness Gap | G14: REC-GOV-002-NS | H14: No | I14: AI Council Governance and Framework Charter
A15: GOV-002 | B15: Not applicable | C15: GOV-002|Not applicable | E15: Exclude | F15: Review Required | G15: REC-GOV-002-NA | H15: No | I15: AI Council Governance and Framework Charter
A16: GOV-003 | B16: No formal AI governance authority exists to review or stop AI initiatives | C16: GOV-003|No formal AI governance authority exists to review or stop AI initiatives | D16: 1 | E16: Include | F16: Governance Authority Gap | G16: REC-GOV-003-L1 | H16: No | I16: AI Council Governance and Framework Charter
A17: GOV-003 | B17: The council or review group may provide informal guidance, but cannot formally approve, pause, or stop projects | C17: GOV-003|The council or review group may provide informal guidance, but cannot formally approve, pause, or stop projects | D17: 2 | E17: Include | F17: Advisory-Only Governance | G17: REC-GOV-003-L1 | H17: No | I17: AI Council Governance and Framework Charter
A18: GOV-003 | B18: The council can review AI initiatives, but its authority to enforce decisions is unclear or inconsistently applied | C18: GOV-003|The council can review AI initiatives, but its authority to enforce decisions is unclear or inconsistently applied | D18: 3 | E18: Include | F18: Partial Capability | G18: REC-GOV-003-L3 | H18: No | I18: AI Council Governance and Framework Charter
A19: GOV-003 | B19: The council has documented authority to approve, pause, escalate, or stop AI initiatives based on defined risk criteria | C19: GOV-003|The council has documented authority to approve, pause, escalate, or stop AI initiatives based on defined risk criteria | D19: 4 | E19: Include | F19: Mature Capability | G19: REC-GOV-003-L4 | H19: Yes | I19: AI Council Governance and Framework Charter
A20: GOV-003 | B20: The council has formal decision rights, escalation authority, auditability, and enforcement mechanisms integrated into funding, delivery, and production release processes | C20: GOV-003|The council has formal decision rights, escalation authority, auditability, and enforcement mechanisms integrated into funding, delivery, and production release processes | D20: 5 | E20: Include | F20: Optimized Capability | G20: REC-GOV-003-L5 | H20: Yes | I20: AI Council Governance and Framework Charter
A21: GOV-003 | B21: Not sure | C21: GOV-003|Not sure | E21: Exclude | F21: Awareness Gap | G21: REC-GOV-003-NS | H21: No | I21: AI Council Governance and Framework Charter
A22: GOV-003 | B22: Not applicable | C22: GOV-003|Not applicable | E22: Exclude | F22: Review Required | G22: REC-GOV-003-NA | H22: No | I22: AI Council Governance and Framework Charter
A23: GOV-004 | B23: No recurring AI governance meeting or review cadence exists | C23: GOV-004|No recurring AI governance meeting or review cadence exists | D23: 1 | E23: Include | F23: Governance Gap | G23: REC-GOV-004-L1 | H23: No | I23: AI Council Governance and Framework Charter
A24: GOV-004 | B24: AI governance discussions occur only as needed or after issues arise | C24: GOV-004|AI governance discussions occur only as needed or after issues arise | D24: 2 | E24: Include | F24: Reactive Governance | G24: REC-GOV-004-L1 | H24: No | I24: AI Council Governance and Framework Charter
A25: GOV-004 | B25: The council meets periodically, but the cadence is not always sufficient to support timely AI review and approval | C25: GOV-004|The council meets periodically, but the cadence is not always sufficient to support timely AI review and approval | D25: 3 | E25: Include | F25: Partial Capability | G25: REC-GOV-004-L3 | H25: No | I25: AI Council Governance and Framework Charter
A26: GOV-004 | B26: The council meets on a defined schedule with a clear intake process, agenda, and service-level expectations for reviews | C26: GOV-004|The council meets on a defined schedule with a clear intake process, agenda, and service-level expectations for reviews | D26: 4 | E26: Include | F26: Mature Capability | G26: REC-GOV-004-L4 | H26: Yes | I26: AI Council Governance and Framework Charter
A27: GOV-004 | B27: The council has a structured cadence, rapid review paths for lower-risk use cases, escalation paths for high-risk use cases, and regularly adjusts cadence based on portfolio demand | C27: GOV-004|The council has a structured cadence, rapid review paths for lower-risk use cases, escalation paths for high-risk use cases, and regularly adjusts cadence based on portfolio demand | D27: 5 | E27: Include | F27: Optimized Capability | G27: REC-GOV-004-L5 | H27: Yes | I27: AI Council Governance and Framework Charter
A28: GOV-004 | B28: Not sure | C28: GOV-004|Not sure | E28: Exclude | F28: Awareness Gap | G28: REC-GOV-004-NS | H28: No | I28: AI Council Governance and Framework Charter
A29: GOV-004 | B29: Not applicable | C29: GOV-004|Not applicable | E29: Exclude | F29: Review Required | G29: REC-GOV-004-NA | H29: No | I29: AI Council Governance and Framework Charter
A30: GOV-005 | B30: No defined escalation path exists for AI risk disagreements | C30: GOV-005|No defined escalation path exists for AI risk disagreements | D30: 1 | E30: Include | F30: Escalation Gap | G30: REC-GOV-005-L1 | H30: No | I30: AI Council Governance and Framework Charter
A31: GOV-005 | B31: Disagreements are handled informally between teams, with no documented tie-breaking authority | C31: GOV-005|Disagreements are handled informally between teams, with no documented tie-breaking authority | D31: 2 | E31: Include | F31: Informal Governance | G31: REC-GOV-005-L1 | H31: No | I31: AI Council Governance and Framework Charter
A32: GOV-005 | B32: An escalation path exists in practice, but it is not consistently documented or understood by stakeholders | C32: GOV-005|An escalation path exists in practice, but it is not consistently documented or understood by stakeholders | D32: 3 | E32: Include | F32: Partial Capability | G32: REC-GOV-005-L3 | H32: No | I32: AI Council Governance and Framework Charter
A33: GOV-005 | B33: A documented escalation path defines who makes final decisions when teams disagree on AI risk level or approval status | C33: GOV-005|A documented escalation path defines who makes final decisions when teams disagree on AI risk level or approval status | D33: 4 | E33: Include | F33: Mature Capability | G33: REC-GOV-005-L4 | H33: Yes | I33: AI Council Governance and Framework Charter
A34: GOV-005 | B34: Escalation paths, decision rights, risk ownership, audit trails, and executive tie-breaking authority are formally embedded into the AI governance process | C34: GOV-005|Escalation paths, decision rights, risk ownership, audit trails, and executive tie-breaking authority are formally embedded into the AI governance process | D34: 5 | E34: Include | F34: Optimized Capability | G34: REC-GOV-005-L5 | H34: Yes | I34: AI Council Governance and Framework Charter
A35: GOV-005 | B35: Not sure | C35: GOV-005|Not sure | E35: Exclude | F35: Awareness Gap | G35: REC-GOV-005-NS | H35: No | I35: AI Council Governance and Framework Charter
A36: GOV-005 | B36: Not applicable | C36: GOV-005|Not applicable | E36: Exclude | F36: Review Required | G36: REC-GOV-005-NA | H36: No | I36: AI Council Governance and Framework Charter
A37: GOV-006 | B37: No formal risk tiering system exists for AI use cases | C37: GOV-006|No formal risk tiering system exists for AI use cases | D37: 1 | E37: Include | F37: Risk Management Gap | G37: REC-GOV-006-L1 | H37: No | I37: AI Council Governance and Framework Charter
A38: GOV-006 | B38: AI risk is considered informally, but there is no consistent rubric or classification process | C38: GOV-006|AI risk is considered informally, but there is no consistent rubric or classification process | D38: 2 | E38: Include | F38: Informal Risk Management | G38: REC-GOV-006-L1 | H38: No | I38: AI Council Governance and Framework Charter
A39: GOV-006 | B39: A basic risk classification approach exists, but criteria or oversight requirements are inconsistently applied | C39: GOV-006|A basic risk classification approach exists, but criteria or oversight requirements are inconsistently applied | D39: 3 | E39: Include | F39: Partial Capability | G39: REC-GOV-006-L3 | H39: No | I39: AI Council Governance and Framework Charter
A40: GOV-006 | B40: AI use cases are classified into defined risk tiers, and each tier triggers specific review, approval, documentation, and oversight requirements | C40: GOV-006|AI use cases are classified into defined risk tiers, and each tier triggers specific review, approval, documentation, and oversight requirements | D40: 4 | E40: Include | F40: Mature Capability | G40: REC-GOV-006-L4 | H40: Yes | I40: AI Council Governance and Framework Charter
A41: GOV-006 | B41: AI risk tiering is standardized, documented, auditable, aligned to regulatory frameworks, and integrated into intake, delivery, vendor review, monitoring, and production release processes | C41: GOV-006|AI risk tiering is standardized, documented, auditable, aligned to regulatory frameworks, and integrated into intake, delivery, vendor review, monitoring, and production release processes | D41: 5 | E41: Include | F41: Optimized Capability | G41: REC-GOV-006-L5 | H41: Yes | I41: AI Council Governance and Framework Charter
A42: GOV-006 | B42: Not sure | C42: GOV-006|Not sure | E42: Exclude | F42: Awareness Gap | G42: REC-GOV-006-NS | H42: No | I42: AI Council Governance and Framework Charter
A43: GOV-006 | B43: Not applicable | C43: GOV-006|Not applicable | E43: Exclude | F43: Review Required | G43: REC-GOV-006-NA | H43: No | I43: AI Council Governance and Framework Charter
A44: GOV-007 | B44: Responsible AI principles are not formally defined | C44: GOV-007|Responsible AI principles are not formally defined | D44: 1 | E44: Include | F44: Responsible AI Gap | G44: REC-GOV-007-L1 | H44: No | I44: AI Council Governance and Framework Charter
A45: GOV-007 | B45: Responsible AI principles are discussed in general terms, but are not documented or measured | C45: GOV-007|Responsible AI principles are discussed in general terms, but are not documented or measured | D45: 2 | E45: Include | F45: Principles Without Controls | G45: REC-GOV-007-L1 | H45: No | I45: AI Council Governance and Framework Charter
A46: GOV-007 | B46: Responsible AI principles are documented, but technical metrics, thresholds, or testing expectations are limited or inconsistent | C46: GOV-007|Responsible AI principles are documented, but technical metrics, thresholds, or testing expectations are limited or inconsistent | D46: 3 | E46: Include | F46: Partial Capability | G46: REC-GOV-007-L3 | H46: No | I46: AI Council Governance and Framework Charter
A47: GOV-007 | B47: Responsible AI principles are documented and supported by defined testing practices, review criteria, and measurable thresholds where applicable | C47: GOV-007|Responsible AI principles are documented and supported by defined testing practices, review criteria, and measurable thresholds where applicable | D47: 4 | E47: Include | F47: Mature Capability | G47: REC-GOV-007-L4 | H47: Yes | I47: AI Council Governance and Framework Charter
A48: GOV-007 | B48: Responsible AI standards are measurable, auditable, embedded into delivery and monitoring processes, and tailored by use case risk level and regulatory context | C48: GOV-007|Responsible AI standards are measurable, auditable, embedded into delivery and monitoring processes, and tailored by use case risk level and regulatory context | D48: 5 | E48: Include | F48: Optimized Capability | G48: REC-GOV-007-L5 | H48: Yes | I48: AI Council Governance and Framework Charter
A49: GOV-007 | B49: Not sure | C49: GOV-007|Not sure | E49: Exclude | F49: Awareness Gap | G49: REC-GOV-007-NS | H49: No | I49: AI Council Governance and Framework Charter
A50: GOV-007 | B50: Not applicable | C50: GOV-007|Not applicable | E50: Exclude | F50: Review Required | G50: REC-GOV-007-NA | H50: No | I50: AI Council Governance and Framework Charter
A51: GOV-008 | B51: No policy or guidance exists for employee use of public or unapproved AI tools | C51: GOV-008|No policy or guidance exists for employee use of public or unapproved AI tools | D51: 1 | E51: Include | F51: Shadow AI Risk | G51: REC-GOV-008-L1 | H51: No | I51: AI Council Governance and Framework Charter
A52: GOV-008 | B52: Informal guidance exists, but employees may still use public AI tools without clear rules or oversight | C52: GOV-008|Informal guidance exists, but employees may still use public AI tools without clear rules or oversight | D52: 2 | E52: Include | F52: Unmanaged Adoption | G52: REC-GOV-008-L1 | H52: No | I52: AI Council Governance and Framework Charter
A53: GOV-008 | B53: A policy exists, but communication, enforcement, approved alternatives, or monitoring are limited | C53: GOV-008|A policy exists, but communication, enforcement, approved alternatives, or monitoring are limited | D53: 3 | E53: Include | F53: Partial Capability | G53: REC-GOV-008-L3 | H53: No | I53: AI Council Governance and Framework Charter
A54: GOV-008 | B54: A documented policy defines acceptable and prohibited AI use, approved tools, data handling rules, and employee responsibilities | C54: GOV-008|A documented policy defines acceptable and prohibited AI use, approved tools, data handling rules, and employee responsibilities | D54: 4 | E54: Include | F54: Mature Capability | G54: REC-GOV-008-L4 | H54: Yes | I54: AI Council Governance and Framework Charter
A55: GOV-008 | B55: Shadow AI is actively managed through policy, training, approved enterprise tools, monitoring, exception handling, and periodic compliance review | C55: GOV-008|Shadow AI is actively managed through policy, training, approved enterprise tools, monitoring, exception handling, and periodic compliance review | D55: 5 | E55: Include | F55: Optimized Capability | G55: REC-GOV-008-L5 | H55: Yes | I55: AI Council Governance and Framework Charter
A56: GOV-008 | B56: Not sure | C56: GOV-008|Not sure | E56: Exclude | F56: Awareness Gap | G56: REC-GOV-008-NS | H56: No | I56: AI Council Governance and Framework Charter
A57: GOV-008 | B57: Not applicable | C57: GOV-008|Not applicable | E57: Exclude | F57: Review Required | G57: REC-GOV-008-NA | H57: No | I57: AI Council Governance and Framework Charter
A58: GOV-009 | B58: No standard AI documentation is required before deployment | C58: GOV-009|No standard AI documentation is required before deployment | D58: 1 | E58: Include | F58: Documentation Gap | G58: REC-GOV-009-L1 | H58: No | I58: AI Council Governance and Framework Charter
A59: GOV-009 | B59: Documentation is created inconsistently and varies by team or project | C59: GOV-009|Documentation is created inconsistently and varies by team or project | D59: 2 | E59: Include | F59: Inconsistent Practice | G59: REC-GOV-009-L1 | H59: No | I59: AI Council Governance and Framework Charter
A60: GOV-009 | B60: A standard template exists, but completion, review, or enforcement is inconsistent | C60: GOV-009|A standard template exists, but completion, review, or enforcement is inconsistent | D60: 3 | E60: Include | F60: Partial Capability | G60: REC-GOV-009-L3 | H60: No | I60: AI Council Governance and Framework Charter
A61: GOV-009 | B61: AI solutions require standard documentation before deployment, such as model cards, AI fact sheets, risk assessments, data descriptions, and approval records | C61: GOV-009|AI solutions require standard documentation before deployment, such as model cards, AI fact sheets, risk assessments, data descriptions, and approval records | D61: 4 | E61: Include | F61: Mature Capability | G61: REC-GOV-009-L4 | H61: Yes | I61: AI Council Governance and Framework Charter
A62: GOV-009 | B62: AI documentation is standardized, reviewed, version-controlled, auditable, tied to risk tiering, and maintained throughout the solution lifecycle | C62: GOV-009|AI documentation is standardized, reviewed, version-controlled, auditable, tied to risk tiering, and maintained throughout the solution lifecycle | D62: 5 | E62: Include | F62: Optimized Capability | G62: REC-GOV-009-L5 | H62: Yes | I62: AI Council Governance and Framework Charter
A63: GOV-009 | B63: Not sure | C63: GOV-009|Not sure | E63: Exclude | F63: Awareness Gap | G63: REC-GOV-009-NS | H63: No | I63: AI Council Governance and Framework Charter
A64: GOV-009 | B64: Not applicable | C64: GOV-009|Not applicable | E64: Exclude | F64: Review Required | G64: REC-GOV-009-NA | H64: No | I64: AI Council Governance and Framework Charter
A65: GOV-010 | B65: AI governance is not mapped to external regulations, standards, or risk frameworks | C65: GOV-010|AI governance is not mapped to external regulations, standards, or risk frameworks | D65: 1 | E65: Include | F65: Regulatory Readiness Gap | G65: REC-GOV-010-L1 | H65: No | I65: AI Council Governance and Framework Charter
A66: GOV-010 | B66: The organization is aware of AI regulations and frameworks, but alignment is informal or not documented | C66: GOV-010|The organization is aware of AI regulations and frameworks, but alignment is informal or not documented | D66: 2 | E66: Include | F66: Informal Alignment | G66: REC-GOV-010-L1 | H66: No | I66: AI Council Governance and Framework Charter
A67: GOV-010 | B67: Some AI policies or controls reference external frameworks, but coverage is incomplete or inconsistently maintained | C67: GOV-010|Some AI policies or controls reference external frameworks, but coverage is incomplete or inconsistently maintained | D67: 3 | E67: Include | F67: Partial Capability | G67: REC-GOV-010-L3 | H67: No | I67: AI Council Governance and Framework Charter
A68: GOV-010 | B68: AI governance is mapped to relevant frameworks or regulations, such as NIST AI RMF, ISO/IEC 42001, industry requirements, or applicable laws | C68: GOV-010|AI governance is mapped to relevant frameworks or regulations, such as NIST AI RMF, ISO/IEC 42001, industry requirements, or applicable laws | D68: 4 | E68: Include | F68: Mature Capability | G68: REC-GOV-010-L4 | H68: Yes | I68: AI Council Governance and Framework Charter
A69: GOV-010 | B69: Regulatory and standards alignment is actively maintained, audited, assigned to control owners, and integrated into governance, risk tiering, vendor review, and delivery processes | C69: GOV-010|Regulatory and standards alignment is actively maintained, audited, assigned to control owners, and integrated into governance, risk tiering, vendor review, and delivery processes | D69: 5 | E69: Include | F69: Optimized Capability | G69: REC-GOV-010-L5 | H69: Yes | I69: AI Council Governance and Framework Charter
A70: GOV-010 | B70: Not sure | C70: GOV-010|Not sure | E70: Exclude | F70: Awareness Gap | G70: REC-GOV-010-NS | H70: No | I70: AI Council Governance and Framework Charter
A71: GOV-010 | B71: Not applicable | C71: GOV-010|Not applicable | E71: Exclude | F71: Review Required | G71: REC-GOV-010-NA | H71: No | I71: AI Council Governance and Framework Charter
A72: GOV-011 | B72: No central inventory of AI models or AI-enabled tools exists | C72: GOV-011|No central inventory of AI models or AI-enabled tools exists | D72: 1 | E72: Include | F72: Inventory Gap | G72: REC-GOV-011-L1 | H72: No | I72: AI Council Governance and Framework Charter
A73: GOV-011 | B73: Some teams maintain local lists of their own models, but there is no enterprise-wide view | C73: GOV-011|Some teams maintain local lists of their own models, but there is no enterprise-wide view | D73: 2 | E73: Include | F73: Fragmented Inventory | G73: REC-GOV-011-L1 | H73: No | I73: AI Council Governance and Framework Charter
A74: GOV-011 | B74: A central inventory exists, but it is incomplete, manually maintained, or omits embedded vendor AI capabilities | C74: GOV-011|A central inventory exists, but it is incomplete, manually maintained, or omits embedded vendor AI capabilities | D74: 3 | E74: Include | F74: Partial Capability | G74: REC-GOV-011-L3 | H74: No | I74: AI Council Governance and Framework Charter
A75: GOV-011 | B75: A maintained central inventory captures internally built models, fine-tuned models, and AI-enabled vendor capabilities, with assigned owners and basic metadata | C75: GOV-011|A maintained central inventory captures internally built models, fine-tuned models, and AI-enabled vendor capabilities, with assigned owners and basic metadata | D75: 4 | E75: Include | F75: Mature Capability | G75: REC-GOV-011-L4 | H75: Yes | I75: AI Council Governance and Framework Charter
A76: GOV-011 | B76: The AI inventory is authoritative, integrated with procurement, risk tiering, monitoring, and the change management process, and is reviewed on a defined cadence | C76: GOV-011|The AI inventory is authoritative, integrated with procurement, risk tiering, monitoring, and the change management process, and is reviewed on a defined cadence | D76: 5 | E76: Include | F76: Optimized Capability | G76: REC-GOV-011-L5 | H76: Yes | I76: AI Council Governance and Framework Charter
A77: GOV-011 | B77: Not sure | C77: GOV-011|Not sure | E77: Exclude | F77: Awareness Gap | G77: REC-GOV-011-NS | H77: No | I77: AI Council Governance and Framework Charter
A78: GOV-011 | B78: Not applicable | C78: GOV-011|Not applicable | E78: Exclude | F78: Review Required | G78: REC-GOV-011-NA | H78: No | I78: AI Council Governance and Framework Charter
A79: GOV-012 | B79: Vendor AI is not assessed for AI-specific risks during procurement | C79: GOV-012|Vendor AI is not assessed for AI-specific risks during procurement | D79: 1 | E79: Include | F79: Vendor Risk Gap | G79: REC-GOV-012-L1 | H79: No | I79: AI Council Governance and Framework Charter
A80: GOV-012 | B80: Procurement reviews vendor AI informally, but there is no required AI risk questionnaire or contract language | C80: GOV-012|Procurement reviews vendor AI informally, but there is no required AI risk questionnaire or contract language | D80: 2 | E80: Include | F80: Informal Vendor Review | G80: REC-GOV-012-L1 | H80: No | I80: AI Council Governance and Framework Charter
A81: GOV-012 | B81: An AI vendor review exists, but coverage of transparency, training data, audit rights, and model updates is inconsistent | C81: GOV-012|An AI vendor review exists, but coverage of transparency, training data, audit rights, and model updates is inconsistent | D81: 3 | E81: Include | F81: Partial Capability | G81: REC-GOV-012-L3 | H81: No | I81: AI Council Governance and Framework Charter
A82: GOV-012 | B82: Vendor AI is subject to a defined AI risk assessment, with documented contract requirements for transparency, model documentation, change notification, and audit or attestation rights | C82: GOV-012|Vendor AI is subject to a defined AI risk assessment, with documented contract requirements for transparency, model documentation, change notification, and audit or attestation rights | D82: 4 | E82: Include | F82: Mature Capability | G82: REC-GOV-012-L4 | H82: Yes | I82: AI Council Governance and Framework Charter
A83: GOV-012 | B83: Vendor AI risk is continuously managed through risk-tiered procurement, contractual controls, ongoing attestation, monitoring of vendor model changes, and integration with the AI inventory | C83: GOV-012|Vendor AI risk is continuously managed through risk-tiered procurement, contractual controls, ongoing attestation, monitoring of vendor model changes, and integration with the AI inventory | D83: 5 | E83: Include | F83: Optimized Capability | G83: REC-GOV-012-L5 | H83: Yes | I83: AI Council Governance and Framework Charter
A84: GOV-012 | B84: Not sure | C84: GOV-012|Not sure | E84: Exclude | F84: Awareness Gap | G84: REC-GOV-012-NS | H84: No | I84: AI Council Governance and Framework Charter
A85: GOV-012 | B85: Not applicable | C85: GOV-012|Not applicable | E85: Exclude | F85: Review Required | G85: REC-GOV-012-NA | H85: No | I85: AI Council Governance and Framework Charter
A86: GOV-013 | B86: AI models are not actively monitored after deployment | C86: GOV-013|AI models are not actively monitored after deployment | D86: 1 | E86: Include | F86: Monitoring Gap | G86: REC-GOV-013-L1 | H86: No | I86: AI Council Governance and Framework Charter
A87: GOV-013 | B87: Monitoring is informal, ad-hoc, or only happens when an issue is reported | C87: GOV-013|Monitoring is informal, ad-hoc, or only happens when an issue is reported | D87: 2 | E87: Include | F87: Reactive Monitoring | G87: REC-GOV-013-L1 | H87: No | I87: AI Council Governance and Framework Charter
A88: GOV-013 | B88: Some models are monitored, but coverage, metrics, thresholds, or alerting are inconsistent across the AI portfolio | C88: GOV-013|Some models are monitored, but coverage, metrics, thresholds, or alerting are inconsistent across the AI portfolio | D88: 3 | E88: Include | F88: Partial Capability | G88: REC-GOV-013-L3 | H88: No | I88: AI Council Governance and Framework Charter
A89: GOV-013 | B89: Production AI models are monitored against defined metrics for performance, drift, and bias, with alerting and assigned owners for response | C89: GOV-013|Production AI models are monitored against defined metrics for performance, drift, and bias, with alerting and assigned owners for response | D89: 4 | E89: Include | F89: Mature Capability | G89: REC-GOV-013-L4 | H89: Yes | I89: AI Council Governance and Framework Charter
A90: GOV-013 | B90: Monitoring is risk-tiered, automated, integrated with retraining and incident response, includes drift and fairness signals, and feeds continuous improvement of the AI portfolio | C90: GOV-013|Monitoring is risk-tiered, automated, integrated with retraining and incident response, includes drift and fairness signals, and feeds continuous improvement of the AI portfolio | D90: 5 | E90: Include | F90: Optimized Capability | G90: REC-GOV-013-L5 | H90: Yes | I90: AI Council Governance and Framework Charter
A91: GOV-013 | B91: Not sure | C91: GOV-013|Not sure | E91: Exclude | F91: Awareness Gap | G91: REC-GOV-013-NS | H91: No | I91: AI Council Governance and Framework Charter
A92: GOV-013 | B92: Not applicable | C92: GOV-013|Not applicable | E92: Exclude | F92: Review Required | G92: REC-GOV-013-NA | H92: No | I92: AI Council Governance and Framework Charter
A93: GOV-014 | B93: No AI-specific incident response plan exists | C93: GOV-014|No AI-specific incident response plan exists | D93: 1 | E93: Include | F93: Incident Response Gap | G93: REC-GOV-014-L1 | H93: No | I93: AI Council Governance and Framework Charter
A94: GOV-014 | B94: AI incidents would be handled informally or through general IT incident processes, without AI-specific playbooks | C94: GOV-014|AI incidents would be handled informally or through general IT incident processes, without AI-specific playbooks | D94: 2 | E94: Include | F94: Generic IR Only | G94: REC-GOV-014-L1 | H94: No | I94: AI Council Governance and Framework Charter
A95: GOV-014 | B95: Some AI incident response procedures exist, but they are incomplete, untested, or not consistently communicated | C95: GOV-014|Some AI incident response procedures exist, but they are incomplete, untested, or not consistently communicated | D95: 3 | E95: Include | F95: Partial Capability | G95: REC-GOV-014-L3 | H95: No | I95: AI Council Governance and Framework Charter
A96: GOV-014 | B96: A documented AI incident response plan defines triage, model disable procedures, communications, regulator notification triggers, and post-incident review | C96: GOV-014|A documented AI incident response plan defines triage, model disable procedures, communications, regulator notification triggers, and post-incident review | D96: 4 | E96: Include | F96: Mature Capability | G96: REC-GOV-014-L4 | H96: Yes | I96: AI Council Governance and Framework Charter
A97: GOV-014 | B97: AI incident response is rehearsed, integrated with enterprise incident management, supported by automated kill-switch capability, and continuously improved through lessons learned | C97: GOV-014|AI incident response is rehearsed, integrated with enterprise incident management, supported by automated kill-switch capability, and continuously improved through lessons learned | D97: 5 | E97: Include | F97: Optimized Capability | G97: REC-GOV-014-L5 | H97: Yes | I97: AI Council Governance and Framework Charter
A98: GOV-014 | B98: Not sure | C98: GOV-014|Not sure | E98: Exclude | F98: Awareness Gap | G98: REC-GOV-014-NS | H98: No | I98: AI Council Governance and Framework Charter
A99: GOV-014 | B99: Not applicable | C99: GOV-014|Not applicable | E99: Exclude | F99: Review Required | G99: REC-GOV-014-NA | H99: No | I99: AI Council Governance and Framework Charter
A100: GOV-015 | B100: No dedicated budget, people, or tools are allocated to AI governance | C100: GOV-015|No dedicated budget, people, or tools are allocated to AI governance | D100: 1 | E100: Include | F100: Resourcing Gap | G100: REC-GOV-015-L1 | H100: No | I100: AI Council Governance and Framework Charter
...

Sheet Recommendations Library
A1: Recommendation ID | B1: Question ID | C1: Trigger Band | D1: Domain | E1: Capability | F1: Recommendation Title | G1: Recommended Action | H1: Priority | I1: Roadmap Horizon
A2: REC-GOV-001-L1 | B2: GOV-001 | C2: L1 | D2: AI Council Governance and Framework Charter | E2: AI Executive Accountability | F2: Establish baseline AI Executive Accountability | G2: AI Executive Accountability is currently absent or ad-hoc. Stand up the foundational practice: assign an owner, document scope and intent, and define a minimum standard the organization will operate against. Use this as the basis for the next maturity step rather than attempting an enterprise-wide rollout. | H2: High | I2: 0-3 months
A3: REC-GOV-001-L3 | B3: GOV-001 | C3: L3 | D3: AI Council Governance and Framework Charter | E3: AI Executive Accountability | F3: Formalize and standardize AI Executive Accountability | G3: AI Executive Accountability exists in partial form. Document standards, decision rights, and review cadence; ensure consistent application across the AI portfolio and close coverage gaps for in-scope use cases or teams. | H3: Medium | I3: 3-6 months
A4: REC-GOV-001-L4 | B4: GOV-001 | C4: L4 | D4: AI Council Governance and Framework Charter | E4: AI Executive Accountability | F4: Integrate AI Executive Accountability into the operating model | G4: AI Executive Accountability is mature. Strengthen by embedding it into delivery, monitoring, and governance processes; tie outcomes to measurable KPIs and assigned owners; align with the AI risk tier and regulatory context. | H4: Medium | I4: 6-12 months
A5: REC-GOV-001-L5 | B5: GOV-001 | C5: L5 | D5: AI Council Governance and Framework Charter | E5: AI Executive Accountability | F5: Sustain and continuously improve AI Executive Accountability | G5: AI Executive Accountability is optimized. Maintain through scheduled review, internal/external benchmarking, and refinement based on incidents, audit findings, and emerging practices. Re-evaluate as the AI portfolio, regulations, and capabilities evolve. | H5: Low | I5: 12+ months
A6: REC-GOV-001-NS | B6: GOV-001 | C6: NS | D6: AI Council Governance and Framework Charter | E6: AI Executive Accountability | F6: Close awareness gap on AI Executive Accountability | G6: The respondent is unsure of the current state. Engage relevant stakeholders (governance, delivery, business sponsors) to confirm, document, and communicate the current state of AI Executive Accountability; treat as an awareness gap to address before scoring this capability. | H6: Medium | I6: 0-3 months
A7: REC-GOV-001-NA | B7: GOV-001 | C7: NA | D7: AI Council Governance and Framework Charter | E7: AI Executive Accountability | F7: Validate applicability of AI Executive Accountability | G7: The respondent indicated AI Executive Accountability is not applicable. Validate with the consultant whether scope, context, or question wording should be adjusted; confirm there are no risk implications of treating this capability as out of scope. | H7: Low | I7: Out of band
A8: REC-GOV-002-L1 | B8: GOV-002 | C8: L1 | D8: AI Council Governance and Framework Charter | E8: Cross-Functional AI Governance | F8: Establish baseline Cross-Functional AI Governance | G8: Cross-Functional AI Governance is currently absent or ad-hoc. Stand up the foundational practice: assign an owner, document scope and intent, and define a minimum standard the organization will operate against. Use this as the basis for the next maturity step rather than attempting an enterprise-wide rollout. | H8: High | I8: 0-3 months
A9: REC-GOV-002-L3 | B9: GOV-002 | C9: L3 | D9: AI Council Governance and Framework Charter | E9: Cross-Functional AI Governance | F9: Formalize and standardize Cross-Functional AI Governance | G9: Cross-Functional AI Governance exists in partial form. Document standards, decision rights, and review cadence; ensure consistent application across the AI portfolio and close coverage gaps for in-scope use cases or teams. | H9: Medium | I9: 3-6 months
A10: REC-GOV-002-L4 | B10: GOV-002 | C10: L4 | D10: AI Council Governance and Framework Charter | E10: Cross-Functional AI Governance | F10: Integrate Cross-Functional AI Governance into the operating model | G10: Cross-Functional AI Governance is mature. Strengthen by embedding it into delivery, monitoring, and governance processes; tie outcomes to measurable KPIs and assigned owners; align with the AI risk tier and regulatory context. | H10: Medium | I10: 6-12 months
A11: REC-GOV-002-L5 | B11: GOV-002 | C11: L5 | D11: AI Council Governance and Framework Charter | E11: Cross-Functional AI Governance | F11: Sustain and continuously improve Cross-Functional AI Governance | G11: Cross-Functional AI Governance is optimized. Maintain through scheduled review, internal/external benchmarking, and refinement based on incidents, audit findings, and emerging practices. Re-evaluate as the AI portfolio, regulations, and capabilities evolve. | H11: Low | I11: 12+ months
A12: REC-GOV-002-NS | B12: GOV-002 | C12: NS | D12: AI Council Governance and Framework Charter | E12: Cross-Functional AI Governance | F12: Close awareness gap on Cross-Functional AI Governance | G12: The respondent is unsure of the current state. Engage relevant stakeholders (governance, delivery, business sponsors) to confirm, document, and communicate the current state of Cross-Functional AI Governance; treat as an awareness gap to address before scoring this capability. | H12: Medium | I12: 0-3 months
... A931: REC-RAC-015-NA | B931: RAC-015 | C931: NA | D931: RACI Matrix | E931: Vendor Model Change Awareness | F931: Validate applicability of Vendor Model Change Awareness | G931: The respondent indicated Vendor Model Change Awareness is not applicable. Validate with the consultant whether scope, context, or question wording should be adjusted; confirm there are no risk implications of treating this capability as out of scope. | H931: Low | I931: Out of band

Sheet Recommendations Output
A1: Question ID | B1: Domain | C1: Capability | D1: Selected Response | E1: Hidden Score | F1: Gap Flag | G1: Recommendation ID | H1: Recommendation Title | I1: Recommended Action | J1: Priority | K1: Roadmap Horizon
A2: =Survey!$A2 -> GOV-001 | B2: =Survey!$B2 -> AI Council Governance and Framework Charter | C2: =Survey!$D2 -> AI Executive Accountability | D2: =Survey!$J2 -> A named executive owns enterprise AI strategy, governance, funding, and prioritization | E2: =Survey!$K2 -> 4 | F2: =Survey!$M2 -> Mature Capability | G2: =Survey!$N2 -> REC-GOV-001-L4 | H2: =IFERROR(_xludf.XLOOKUP(G2,tbl_RecLibrary[Recommendation ID],tbl_RecLibrary[Recommendation Title]),"") | I2: =IFERROR(_xludf.XLOOKUP(G2,tbl_RecLibrary[Recommendation ID],tbl_RecLibrary[Recommended Action]),"") | J2: =IFERROR(_xludf.XLOOKUP(G2,tbl_RecLibrary[Recommendation ID],tbl_RecLibrary[Priority]),"") | K2: =IFERROR(_xludf.XLOOKUP(G2,tbl_RecLibrary[Recommendation ID],tbl_RecLibrary[Roadmap Horizon]),"")
A3: =Survey!$A3 -> GOV-002 | B3: =Survey!$B3 -> AI Council Governance and Framework Charter | C3: =Survey!$D3 -> Cross-Functional AI Governance | D3: =Survey!$J3 -> The governance body includes consistent representation from IT, business units, legal, security/risk, HR, and data/analytics, with defined roles and decision rights | E3: =Survey!$K3 -> 4 | F3: =Survey!$M3 -> Mature Capability | G3: =Survey!$N3 -> REC-GOV-002-L4 | H3: =IFERROR(_xludf.XLOOKUP(G3,tbl_RecLibrary[Recommendation ID],tbl_RecLibrary[Recommendation Title]),"") | I3: =IFERROR(_xludf.XLOOKUP(G3,tbl_RecLibrary[Recommendation ID],tbl_RecLibrary[Recommended Action]),"") | J3: =IFERROR(_xludf.XLOOKUP(G3,tbl_RecLibrary[Recommendation ID],tbl_RecLibrary[Priority]),"") | K3: =IFERROR(_xludf.XLOOKUP(G3,tbl_RecLibrary[Recommendation ID],tbl_RecLibrary[Roadmap Horizon]),"")
A4: =Survey!$A4 -> GOV-003 | B4: =Survey!$B4 -> AI Council Governance and Framework Charter | C4: =Survey!$D4 -> Governance Authority and Decision Rights | D4: =Survey!$J4 -> The council can review AI initiatives, but its authority to enforce decisions is unclear or inconsistently applied | E4: =Survey!$K4 -> 3 | F4: =Survey!$M4 -> Partial Capability | G4: =Survey!$N4 -> REC-GOV-003-L3 | H4: =IFERROR(_xludf.XLOOKUP(G4,tbl_RecLibrary[Recommendation ID],tbl_RecLibrary[Recommendation Title]),"") | I4: =IFERROR(_xludf.XLOOKUP(G4,tbl_RecLibrary[Recommendation ID],tbl_RecLibrary[Recommended Action]),"") | J4: =IFERROR(_xludf.XLOOKUP(G4,tbl_RecLibrary[Recommendation ID],tbl_RecLibrary[Priority]),"") | K4: =IFERROR(_xludf.XLOOKUP(G4,tbl_RecLibrary[Recommendation ID],tbl_RecLibrary[Roadmap Horizon]),"")
A5: =Survey!$A5 -> GOV-004 | B5: =Survey!$B5 -> AI Council Governance and Framework Charter | C5: =Survey!$D5 -> Governance Cadence and Responsiveness | D5: =Survey!$J5 -> The council meets periodically, but the cadence is not always sufficient to support timely AI review and approval | E5: =Survey!$K5 -> 3 | F5: =Survey!$M5 -> Partial Capability | G5: =Survey!$N5 -> REC-GOV-004-L3 | H5: =IFERROR(_xludf.XLOOKUP(G5,tbl_RecLibrary[Recommendation ID],tbl_RecLibrary[Recommendation Title]),"") | I5: =IFERROR(_xludf.XLOOKUP(G5,tbl_RecLibrary[Recommendation ID],tbl_RecLibrary[Recommended Action]),"") | J5: =IFERROR(_xludf.XLOOKUP(G5,tbl_RecLibrary[Recommendation ID],tbl_RecLibrary[Priority]),"") | K5: =IFERROR(_xludf.XLOOKUP(G5,tbl_RecLibrary[Recommendation ID],tbl_RecLibrary[Roadmap Horizon]),"")
A6: =Survey!$A6 -> GOV-005 | B6: =Survey!$B6 -> AI Council Governance and Framework Charter | C6: =Survey!$D6 -> AI Risk Escalation and Tie-Breaking | D6: =Survey!$J6 -> Disagreements are handled informally between teams, with no documented tie-breaking authority | E6: =Survey!$K6 -> 2 | F6: =Survey!$M6 -> Informal Governance | G6: =Survey!$N6 -> REC-GOV-005-L1 | H6: =IFERROR(_xludf.XLOOKUP(G6,tbl_RecLibrary[Recommendation ID],tbl_RecLibrary[Recommendation Title]),"") | I6: =IFERROR(_xludf.XLOOKUP(G6,tbl_RecLibrary[Recommendation ID],tbl_RecLibrary[Recommended Action]),"") | J6: =IFERROR(_xludf.XLOOKUP(G6,tbl_RecLibrary[Recommendation ID],tbl_RecLibrary[Priority]),"") | K6: =IFERROR(_xludf.XLOOKUP(G6,tbl_RecLibrary[Recommendation ID],tbl_RecLibrary[Roadmap Horizon]),"")
A7: =Survey!$A7 -> GOV-006 | B7: =Survey!$B7 -> AI Council Governance and Framework Charter | C7: =Survey!$D7 -> AI Risk Classification | D7: =Survey!$J7 -> AI use cases are classified into defined risk tiers, and each tier triggers specific review, approval, documentation, and oversight requirements | E7: =Survey!$K7 -> 4 | F7: =Survey!$M7 -> Mature Capability | G7: =Survey!$N7 -> REC-GOV-006-L4 | H7: =IFERROR(_xludf.XLOOKUP(G7,tbl_RecLibrary[Recommendation ID],tbl_RecLibrary[Recommendation Title]),"") | I7: =IFERROR(_xludf.XLOOKUP(G7,tbl_RecLibrary[Recommendation ID],tbl_RecLibrary[Recommended Action]),"") | J7: =IFERROR(_xludf.XLOOKUP(G7,tbl_RecLibrary[Recommendation ID],tbl_RecLibrary[Priority]),"") | K7: =IFERROR(_xludf.XLOOKUP(G7,tbl_RecLibrary[Recommendation ID],tbl_RecLibrary[Roadmap Horizon]),"")
A8: =Survey!$A8 -> GOV-007 | B8: =Survey!$B8 -> AI Council Governance and Framework Charter | C8: =Survey!$D8 -> Responsible AI Standards and Metrics | D8: =Survey!$J8 -> Responsible AI principles are discussed in general terms, but are not documented or measured | E8: =Survey!$K8 -> 2 | F8: =Survey!$M8 -> Principles Without Controls | G8: =Survey!$N8 -> REC-GOV-007-L1 | H8: =IFERROR(_xludf.XLOOKUP(G8,tbl_RecLibrary[Recommendation ID],tbl_RecLibrary[Recommendation Title]),"") | I8: =IFERROR(_xludf.XLOOKUP(G8,tbl_RecLibrary[Recommendation ID],tbl_RecLibrary[Recommended Action]),"") | J8: =IFERROR(_xludf.XLOOKUP(G8,tbl_RecLibrary[Recommendation ID],tbl_RecLibrary[Priority]),"") | K8: =IFERROR(_xludf.XLOOKUP(G8,tbl_RecLibrary[Recommendation ID],tbl_RecLibrary[Roadmap Horizon]),"")
A9: =Survey!$A9 -> GOV-008 | B9: =Survey!$B9 -> AI Council Governance and Framework Charter | C9: =Survey!$D9 -> Shadow AI Management | D9: =Survey!$J9 -> Shadow AI is actively managed through policy, training, approved enterprise tools, monitoring, exception handling, and periodic compliance review | E9: =Survey!$K9 -> 5 | F9: =Survey!$M9 -> Optimized Capability | G9: =Survey!$N9 -> REC-GOV-008-L5 | H9: =IFERROR(_xludf.XLOOKUP(G9,tbl_RecLibrary[Recommendation ID],tbl_RecLibrary[Recommendation Title]),"") | I9: =IFERROR(_xludf.XLOOKUP(G9,tbl_RecLibrary[Recommendation ID],tbl_RecLibrary[Recommended Action]),"") | J9: =IFERROR(_xludf.XLOOKUP(G9,tbl_RecLibrary[Recommendation ID],tbl_RecLibrary[Priority]),"") | K9: =IFERROR(_xludf.XLOOKUP(G9,tbl_RecLibrary[Recommendation ID],tbl_RecLibrary[Roadmap Horizon]),"")
A10: =Survey!$A10 -> GOV-009 | B10: =Survey!$B10 -> AI Council Governance and Framework Charter | C10: =Survey!$D10 -> AI Documentation and Deployment Readiness | D10: =Survey!$J10 -> Documentation is created inconsistently and varies by team or project | E10: =Survey!$K10 -> 2 | F10: =Survey!$M10 -> Inconsistent Practice | G10: =Survey!$N10 -> REC-GOV-009-L1 | H10: =IFERROR(_xludf.XLOOKUP(G10,tbl_RecLibrary[Recommendation ID],tbl_RecLibrary[Recommendation Title]),"") | I10: =IFERROR(_xludf.XLOOKUP(G10,tbl_RecLibrary[Recommendation ID],tbl_RecLibrary[Recommended Action]),"") | J10: =IFERROR(_xludf.XLOOKUP(G10,tbl_RecLibrary[Recommendation ID],tbl_RecLibrary[Priority]),"") | K10: =IFERROR(_xludf.XLOOKUP(G10,tbl_RecLibrary[Recommendation ID],tbl_RecLibrary[Roadmap Horizon]),"")
A11: =Survey!$A11 -> GOV-010 | B11: =Survey!$B11 -> AI Council Governance and Framework Charter | C11: =Survey!$D11 -> Regulatory and Standards Alignment | D11: =Survey!$J11 -> Some AI policies or controls reference external frameworks, but coverage is incomplete or inconsistently maintained | E11: =Survey!$K11 -> 3 | F11: =Survey!$M11 -> Partial Capability | G11: =Survey!$N11 -> REC-GOV-010-L3 | H11: =IFERROR(_xludf.XLOOKUP(G11,tbl_RecLibrary[Recommendation ID],tbl_RecLibrary[Recommendation Title]),"") | I11: =IFERROR(_xludf.XLOOKUP(G11,tbl_RecLibrary[Recommendation ID],tbl_RecLibrary[Recommended Action]),"") | J11: =IFERROR(_xludf.XLOOKUP(G11,tbl_RecLibrary[Recommendation ID],tbl_RecLibrary[Priority]),"") | K11: =IFERROR(_xludf.XLOOKUP(G11,tbl_RecLibrary[Recommendation ID],tbl_RecLibrary[Roadmap Horizon]),"")
A12: =Survey!$A12 -> GOV-011 | B12: =Survey!$B12 -> AI Council Governance and Framework Charter | C12: =Survey!$D12 -> AI Asset Inventory | D12: =Survey!$J12 -> A central inventory exists, but it is incomplete, manually maintained, or omits embedded vendor AI capabilities | E12: =Survey!$K12 -> 3 | F12: =Survey!$M12 -> Partial Capability | G12: =Survey!$N12 -> REC-GOV-011-L3 | H12: =IFERROR(_xludf.XLOOKUP(G12,tbl_RecLibrary[Recommendation ID],tbl_RecLibrary[Recommendation Title]),"") | I12: =IFERROR(_xludf.XLOOKUP(G12,tbl_RecLibrary[Recommendation ID],tbl_RecLibrary[Recommended Action]),"") | J12: =IFERROR(_xludf.XLOOKUP(G12,tbl_RecLibrary[Recommendation ID],tbl_RecLibrary[Priority]),"") | K12: =IFERROR(_xludf.XLOOKUP(G12,tbl_RecLibrary[Recommendation ID],tbl_RecLibrary[Roadmap Horizon]),"")
A13: =Survey!$A13 -> GOV-012 | B13: =Survey!$B13 -> AI Council Governance and Framework Charter | C13: =Survey!$D13 -> Third-Party AI Risk | D13: =Survey!$J13 -> An AI vendor review exists, but coverage of transparency, training data, audit rights, and model updates is inconsistent | E13: =Survey!$K13 -> 3 | F13: =Survey!$M13 -> Partial Capability | G13: =Survey!$N13 -> REC-GOV-012-L3 | H13: =IFERROR(_xludf.XLOOKUP(G13,tbl_RecLibrary[Recommendation ID],tbl_RecLibrary[Recommendation Title]),"") | I13: =IFERROR(_xludf.XLOOKUP(G13,tbl_RecLibrary[Recommendation ID],tbl_RecLibrary[Recommended Action]),"") | J13: =IFERROR(_xludf.XLOOKUP(G13,tbl_RecLibrary[Recommendation ID],tbl_RecLibrary[Priority]),"") | K13: =IFERROR(_xludf.XLOOKUP(G13,tbl_RecLibrary[Recommendation ID],tbl_RecLibrary[Roadmap Horizon]),"")
... A19: =Survey!$A19 -> GOV-018 | B19: =Survey!$B19 -> AI Council Governance and Framework Charter | C19: =Survey!$D19 -> Speak-Up Culture for AI Risk | D19: =Survey!$J19 -> A documented, communicated channel allows employees to raise AI concerns, including anonymously, with a defined triage and response process | E19: =Survey!$K19 -> 4 | F19: =Survey!$M19 -> Mature Capability | G19: =Survey!$N19 -> REC-GOV-018-L4 | H19: =IFERROR(_xludf.XLOOKUP(G19,tbl_RecLibrary[Recommendation ID],tbl_RecLibrary[Recommendation Title]),"") | I19: =IFERROR(_xludf.XLOOKUP(G19,tbl_RecLibrary[Recommendation ID],tbl_RecLibrary[Recommended Action]),"") | J19: =IFERROR(_xludf.XLOOKUP(G19,tbl_RecLibrary[Recommendation ID],tbl_RecLibrary[Priority]),"") | K19: =IFERROR(_xludf.XLOOKUP(G19,tbl_RecLibrary[Recommendation ID],tbl_RecLibrary[Roadmap Horizon]),"")
A20: =Survey!$A20 -> STR-001 | B20: =Survey!$B20 -> AI Strategy and Roadmap | C20: =Survey!$D20 -> AI Business Value Articulation | D20: =Survey!#REF! -> #REF! | E20: =Survey!$K20 -> 4 | F20: =Survey!$M20 -> Mature Capability | G20: =Survey!$N20 -> REC-STR-001-L4 | H20: =IFERROR(_xludf.XLOOKUP(G20,tbl_RecLibrary[Recommendation ID],tbl_RecLibrary[Recommendation Title]),"") | I20: =IFERROR(_xludf.XLOOKUP(G20,tbl_RecLibrary[Recommendation ID],tbl_RecLibrary[Recommended Action]),"") | J20: =IFERROR(_xludf.XLOOKUP(G20,tbl_RecLibrary[Recommendation ID],tbl_RecLibrary[Priority]),"") | K20: =IFERROR(_xludf.XLOOKUP(G20,tbl_RecLibrary[Recommendation ID],tbl_RecLibrary[Roadmap Horizon]),"")
A21: =Survey!$A21 -> STR-002 | B21: =Survey!$B21 -> AI Strategy and Roadmap | C21: =Survey!$D21 -> AI Sourcing Strategy | D21: =Survey!$J20 -> Each major AI initiative has a documented business case, named KPI, baseline, target, and accountable owner | E21: =Survey!$K21 -> 4 | F21: =Survey!$M21 -> Mature Capability | G21: =Survey!$N21 -> REC-STR-002-L4 | H21: =IFERROR(_xludf.XLOOKUP(G21,tbl_RecLibrary[Recommendation ID],tbl_RecLibrary[Recommendation Title]),"") | I21: =IFERROR(_xludf.XLOOKUP(G21,tbl_RecLibrary[Recommendation ID],tbl_RecLibrary[Recommended Action]),"") | J21: =IFERROR(_xludf.XLOOKUP(G21,tbl_RecLibrary[Recommendation ID],tbl_RecLibrary[Priority]),"") | K21: =IFERROR(_xludf.XLOOKUP(G21,tbl_RecLibrary[Recommendation ID],tbl_RecLibrary[Roadmap Horizon]),"")
A22: =Survey!$A22 -> STR-003 | B22: =Survey!$B22 -> AI Strategy and Roadmap | C22: =Survey!$D22 -> AI Competitive Strategy | D22: =Survey!$J22 -> Leadership recognizes both parity and differentiation goals, but the portfolio mix is not deliberately managed | E22: =Survey!$K22 -> 3 | F22: =Survey!$M22 -> Partial Capability | G22: =Survey!$N22 -> REC-STR-003-L3 | H22: =IFERROR(_xludf.XLOOKUP(G22,tbl_RecLibrary[Recommendation ID],tbl_RecLibrary[Recommendation Title]),"") | I22: =IFERROR(_xludf.XLOOKUP(G22,tbl_RecLibrary[Recommendation ID],tbl_RecLibrary[Recommended Action]),"") | J22: =IFERROR(_xludf.XLOOKUP(G22,tbl_RecLibrary[Recommendation ID],tbl_RecLibrary[Priority]),"") | K22: =IFERROR(_xludf.XLOOKUP(G22,tbl_RecLibrary[Recommendation ID],tbl_RecLibrary[Roadmap Horizon]),"")
A23: =Survey!$A23 -> STR-004 | B23: =Survey!$B23 -> AI Strategy and Roadmap | C23: =Survey!$D23 -> AI Portfolio Balance | D23: =Survey!$J23 -> One side dominates by default (e.g., all internal productivity, or all customer-facing pilots), with no strategic rationale | E23: =Survey!$K23 -> 2 | F23: =Survey!$M23 -> Imbalanced Portfolio | G23: =Survey!$N23 -> REC-STR-004-L1 | H23: =IFERROR(_xludf.XLOOKUP(G23,tbl_RecLibrary[Recommendation ID],tbl_RecLibrary[Recommendation Title]),"") | I23: =IFERROR(_xludf.XLOOKUP(G23,tbl_RecLibrary[Recommendation ID],tbl_RecLibrary[Recommended Action]),"") | J23: =IFERROR(_xludf.XLOOKUP(G23,tbl_RecLibrary[Recommendation ID],tbl_RecLibrary[Priority]),"") | K23: =IFERROR(_xludf.XLOOKUP(G23,tbl_RecLibrary[Recommendation ID],tbl_RecLibrary[Roadmap Horizon]),"")
A24: =Survey!$A24 -> STR-005 | B24: =Survey!$B24 -> AI Strategy and Roadmap | C24: =Survey!$D24 -> Foundational Data Readiness | D24: =Survey!$J24 -> Data issues are known but not reflected as milestones, dependencies, or funded work in the roadmap | E24: =Survey!$K24 -> 2 | F24: =Survey!$M24 -> Unfunded Data Debt | G24: =Survey!$N24 -> REC-STR-005-L1 | H24: =IFERROR(_xludf.XLOOKUP(G24,tbl_RecLibrary[Recommendation ID],tbl_RecLibrary[Recommendation Title]),"") | I24: =IFERROR(_xludf.XLOOKUP(G24,tbl_RecLibrary[Recommendation ID],tbl_RecLibrary[Recommended Action]),"") | J24: =IFERROR(_xludf.XLOOKUP(G24,tbl_RecLibrary[Recommendation ID],tbl_RecLibrary[Priority]),"") | K24: =IFERROR(_xludf.XLOOKUP(G24,tbl_RecLibrary[Recommendation ID],tbl_RecLibrary[Roadmap Horizon]),"")
A25: =Survey!$A25 -> STR-006 | B25: =Survey!$B25 -> AI Strategy and Roadmap | C25: =Survey!$D25 -> Portfolio Horizon Balance | D25: =Survey!$J25 -> Some short-term and long-term work exists, but the balance is accidental rather than deliberate | E25: =Survey!$K25 -> 2 | F25: =Survey!$M25 -> Unintentional Mix | G25: =Survey!$N25 -> REC-STR-006-L1 | H25: =IFERROR(_xludf.XLOOKUP(G25,tbl_RecLibrary[Recommendation ID],tbl_RecLibrary[Recommendation Title]),"") | I25: =IFERROR(_xludf.XLOOKUP(G25,tbl_RecLibrary[Recommendation ID],tbl_RecLibrary[Recommended Action]),"") | J25: =IFERROR(_xludf.XLOOKUP(G25,tbl_RecLibrary[Recommendation ID],tbl_RecLibrary[Priority]),"") | K25: =IFERROR(_xludf.XLOOKUP(G25,tbl_RecLibrary[Recommendation ID],tbl_RecLibrary[Roadmap Horizon]),"")
A26: =Survey!$A26 -> STR-007 | B26: =Survey!$B26 -> AI Strategy and Roadmap | C26: =Survey!$D26 -> Roadmap Dependency Management | D26: =Survey!$J26 -> Dependencies are known informally by individuals, but not documented or used to sequence work | E26: =Survey!$K26 -> 2 | F26: =Survey!$M26 -> Tribal Knowledge | G26: =Survey!$N26 -> REC-STR-007-L1 | H26: =IFERROR(_xludf.XLOOKUP(G26,tbl_RecLibrary[Recommendation ID],tbl_RecLibrary[Recommendation Title]),"") | I26: =IFERROR(_xludf.XLOOKUP(G26,tbl_RecLibrary[Recommendation ID],tbl_RecLibrary[Recommended Action]),"") | J26: =IFERROR(_xludf.XLOOKUP(G26,tbl_RecLibrary[Recommendation ID],tbl_RecLibrary[Priority]),"") | K26: =IFERROR(_xludf.XLOOKUP(G26,tbl_RecLibrary[Recommendation ID],tbl_RecLibrary[Roadmap Horizon]),"")
A27: =Survey!$A27 -> STR-008 | B27: =Survey!$B27 -> AI Strategy and Roadmap | C27: =Survey!$D27 -> Roadmap Refresh and Project Termination | D27: =Survey!$J27 -> The roadmap is reviewed periodically, but stop/continue decisions are inconsistent or politically difficult | E27: =Survey!$K27 -> 3 | F27: =Survey!$M27 -> Partial Capability | G27: =Survey!$N27 -> REC-STR-008-L3 | H27: =IFERROR(_xludf.XLOOKUP(G27,tbl_RecLibrary[Recommendation ID],tbl_RecLibrary[Recommendation Title]),"") | I27: =IFERROR(_xludf.XLOOKUP(G27,tbl_RecLibrary[Recommendation ID],tbl_RecLibrary[Recommended Action]),"") | J27: =IFERROR(_xludf.XLOOKUP(G27,tbl_RecLibrary[Recommendation ID],tbl_RecLibrary[Priority]),"") | K27: =IFERROR(_xludf.XLOOKUP(G27,tbl_RecLibrary[Recommendation ID],tbl_RecLibrary[Roadmap Horizon]),"")
A28: =Survey!$A28 -> STR-009 | B28: =Survey!$B28 -> AI Strategy and Roadmap | C28: =Survey!$D28 -> AI Talent Strategy | D28: =Survey!$J28 -> Some internal AI capability exists, but key roles (e.g., ML engineering, MLOps, data engineering) are heavily dependent on contractors | E28: =Survey!$K28 -> 2 | F28: =Survey!$M28 -> External Dependency | G28: =Survey!$N28 -> REC-STR-009-L1 | H28: =IFERROR(_xludf.XLOOKUP(G28,tbl_RecLibrary[Recommendation ID],tbl_RecLibrary[Recommendation Title]),"") | I28: =IFERROR(_xludf.XLOOKUP(G28,tbl_RecLibrary[Recommendation ID],tbl_RecLibrary[Recommended Action]),"") | J28: =IFERROR(_xludf.XLOOKUP(G28,tbl_RecLibrary[Recommendation ID],tbl_RecLibrary[Priority]),"") | K28: =IFERROR(_xludf.XLOOKUP(G28,tbl_RecLibrary[Recommendation ID],tbl_RecLibrary[Roadmap Horizon]),"")
A29: =Survey!$A29 -> STR-010 | B29: =Survey!$B29 -> AI Strategy and Roadmap | C29: =Survey!$D29 -> AI Cost Forecasting | D29: =Survey!$J29 -> AI run costs are continuously monitored, attributed to business outcomes, optimized through architecture and model selection, and integrated with FinOps practices | E29: =Survey!$K29 -> 5 | F29: =Survey!$M29 -> Optimized Capability | G29: =Survey!$N29 -> REC-STR-010-L5 | H29: =IFERROR(_xludf.XLOOKUP(G29,tbl_RecLibrary[Recommendation ID],tbl_RecLibrary[Recommendation Title]),"") | I29: =IFERROR(_xludf.XLOOKUP(G29,tbl_RecLibrary[Recommendation ID],tbl_RecLibrary[Recommended Action]),"") | J29: =IFERROR(_xludf.XLOOKUP(G29,tbl_RecLibrary[Recommendation ID],tbl_RecLibrary[Priority]),"") | K29: =IFERROR(_xludf.XLOOKUP(G29,tbl_RecLibrary[Recommendation ID],tbl_RecLibrary[Roadmap Horizon]),"")
A30: =Survey!$A30 -> STR-011 | B30: =Survey!$B30 -> AI Strategy and Roadmap | C30: =Survey!$D30 -> Subject-Matter Expert Engagement | D30: =Survey!$J30 -> Some initiatives have allocated SME time, but the practice is inconsistent across the portfolio | E30: =Survey!$K30 -> 3 | F30: =Survey!$M30 -> Partial Capability | G30: =Survey!$N30 -> REC-STR-011-L3 | H30: =IFERROR(_xludf.XLOOKUP(G30,tbl_RecLibrary[Recommendation ID],tbl_RecLibrary[Recommendation Title]),"") | I30: =IFERROR(_xludf.XLOOKUP(G30,tbl_RecLibrary[Recommendation ID],tbl_RecLibrary[Recommended Action]),"") | J30: =IFERROR(_xludf.XLOOKUP(G30,tbl_RecLibrary[Recommendation ID],tbl_RecLibrary[Priority]),"") | K30: =IFERROR(_xludf.XLOOKUP(G30,tbl_RecLibrary[Recommendation ID],tbl_RecLibrary[Roadmap Horizon]),"")
A31: =Survey!$A31 -> STR-012 | B31: =Survey!$B31 -> AI Strategy and Roadmap | C31: =Survey!$D31 -> End-User AI Enablement | D31: =Survey!$J31 -> A documented workforce AI enablement plan covers role-based training, communications, and adoption measurement for each major AI tool | E31: =Survey!$K31 -> 4 | F31: =Survey!$M31 -> Mature Capability | G31: =Survey!$N31 -> REC-STR-012-L4 | H31: =IFERROR(_xludf.XLOOKUP(G31,tbl_RecLibrary[Recommendation ID],tbl_RecLibrary[Recommendation Title]),"") | I31: =IFERROR(_xludf.XLOOKUP(G31,tbl_RecLibrary[Recommendation ID],tbl_RecLibrary[Recommended Action]),"") | J31: =IFERROR(_xludf.XLOOKUP(G31,tbl_RecLibrary[Recommendation ID],tbl_RecLibrary[Priority]),"") | K31: =IFERROR(_xludf.XLOOKUP(G31,tbl_RecLibrary[Recommendation ID],tbl_RecLibrary[Roadmap Horizon]),"")
A32: =Survey!$A32 -> STR-013 | B32: =Survey!$B32 -> AI Strategy and Roadmap | C32: =Survey!$D32 -> AI Success Definition | D32: =Survey!$J32 -> Multiple success measures exist, but the balance between technical and business measures is inconsistent across initiatives | E32: =Survey!$K32 -> 3 | F32: =Survey!$M32 -> Partial Capability | G32: =Survey!$N32 -> REC-STR-013-L3 | H32: =IFERROR(_xludf.XLOOKUP(G32,tbl_RecLibrary[Recommendation ID],tbl_RecLibrary[Recommendation Title]),"") | I32: =IFERROR(_xludf.XLOOKUP(G32,tbl_RecLibrary[Recommendation ID],tbl_RecLibrary[Recommended Action]),"") | J32: =IFERROR(_xludf.XLOOKUP(G32,tbl_RecLibrary[Recommendation ID],tbl_RecLibrary[Priority]),"") | K32: =IFERROR(_xludf.XLOOKUP(G32,tbl_RecLibrary[Recommendation ID],tbl_RecLibrary[Roadmap Horizon]),"")
A33: =Survey!$A33 -> STR-014 | B33: =Survey!$B33 -> AI Strategy and Roadmap | C33: =Survey!$D33 -> AI Investment Time Horizon | D33: =Survey!$J33 -> AI initiatives have defined time-to-value windows aligned to initiative type (e.g., pilot vs. platform vs. strategic bet) | E33: =Survey!$K33 -> 4 | F33: =Survey!$M33 -> Mature Capability | G33: =Survey!$N33 -> REC-STR-014-L4 | H33: =IFERROR(_xludf.XLOOKUP(G33,tbl_RecLibrary[Recommendation ID],tbl_RecLibrary[Recommendation Title]),"") | I33: =IFERROR(_xludf.XLOOKUP(G33,tbl_RecLibrary[Recommendation ID],tbl_RecLibrary[Recommended Action]),"") | J33: =IFERROR(_xludf.XLOOKUP(G33,tbl_RecLibrary[Recommendation ID],tbl_RecLibrary[Priority]),"") | K33: =IFERROR(_xludf.XLOOKUP(G33,tbl_RecLibrary[Recommendation ID],tbl_RecLibrary[Roadmap Horizon]),"")
... A156: =Survey!$A156 -> RAC-015 | B156: =Survey!$B156 -> RACI Matrix | C156: =Survey!$D156 -> Vendor Model Change Awareness | D156: =Survey!$J156 -> Vendor change awareness is automated, integrated with regression testing, supports rapid response to breaking changes, and feeds vendor risk management | E156: =Survey!$K156 -> 5 | F156: =Survey!$M156 -> Optimized Capability | G156: =Survey!$N156 -> REC-RAC-015-L5 | H156: =IFERROR(_xludf.XLOOKUP(G156,tbl_RecLibrary[Recommendation ID],tbl_RecLibrary[Recommendation Title]),"") | I156: =IFERROR(_xludf.XLOOKUP(G156,tbl_RecLibrary[Recommendation ID],tbl_RecLibrary[Recommended Action]),"") | J156: =IFERROR(_xludf.XLOOKUP(G156,tbl_RecLibrary[Recommendation ID],tbl_RecLibrary[Priority]),"") | K156: =IFERROR(_xludf.XLOOKUP(G156,tbl_RecLibrary[Recommendation ID],tbl_RecLibrary[Roadmap Horizon]),"")

Sheet Dashboard
A1: AI Maturity Assessment — Dashboard
A3: Overall Maturity Score | B3: =IFERROR(ROUND(AVERAGE(#REF!),1),"")
A4: Completion % | B4: =IFERROR(COUNTA(#REF!)/COUNTA(#REF!),0) -> 1
A5: Completed / Total | B5: =COUNTA(#REF!)&" / "&COUNTA(#REF!) -> 1 / 1
A6: Not Sure count | B6: =COUNTIF(#REF!,"Not sure") -> #REF!
A7: Not Applicable count | B7: =COUNTIF(#REF!,"Not applicable") -> #REF!
A9: Domain Maturity Scores
A10: AI Council Governance and Framework Charter | B10: =IFERROR(ROUND(AVERAGEIFS(#REF!,#REF!,A10),1),"")
A11: AI Strategy and Roadmap | B11: =IFERROR(ROUND(AVERAGEIFS(#REF!,#REF!,A11),1),"")
A12: Responsible AI Guidelines | B12: =IFERROR(ROUND(AVERAGEIFS(#REF!,#REF!,A12),1),"")
A13: Performance Measurement Framework | B13: =IFERROR(ROUND(AVERAGEIFS(#REF!,#REF!,A13),1),"")
A14: AI Operating Model Blueprint | B14: =IFERROR(ROUND(AVERAGEIFS(#REF!,#REF!,A14),1),"")
A15: Use Case Prioritization Framework | B15: =IFERROR(ROUND(AVERAGEIFS(#REF!,#REF!,A15),1),"")
A16: Training Program for Council and Business Units | B16: =IFERROR(ROUND(AVERAGEIFS(#REF!,#REF!,A16),1),"")
A17: Change Management and Adoption Plan | B17: =IFERROR(ROUND(AVERAGEIFS(#REF!,#REF!,A17),1),"")
A18: Technology Architecture and Guidance | B18: =IFERROR(ROUND(AVERAGEIFS(#REF!,#REF!,A18),1),"")
A19: RACI Matrix | B19: =IFERROR(ROUND(AVERAGEIFS(#REF!,#REF!,A19),1),"")
A40: Recommendations Triggered — High Priority (score 1-2) | B40: =COUNTIFS(#REF!,"<>",#REF!,"<=2") -> #REF!
A41: Recommendations Triggered — Medium Priority (score 3) | B41: =COUNTIFS(#REF!,"<>",#REF!,3) -> #REF!
A42: Recommendations Triggered — Low Priority (score 4-5) | B42: =COUNTIFS(#REF!,"<>",#REF!,">=4") -> #REF!
A43: Recommendations Triggered — Not Sure / Not Applicable | B43: =COUNTIFS(#REF!,"<>",#REF!,"") -> #REF!

Sheet Gap Analysis
A1: Gap Flag | B1: Count in Survey Responses
A2: Governance Gap | B2: =COUNTIF(#REF!,"Governance Gap") -> #REF!
A3: Partial Capability | B3: =COUNTIF(#REF!,"Partial Capability") -> #REF!
A4: Mature Capability | B4: =COUNTIF(#REF!,"Mature Capability") -> #REF!
A5: Optimized Capability | B5: =COUNTIF(#REF!,"Optimized Capability") -> #REF!
A6: Awareness Gap | B6: =COUNTIF(#REF!,"Awareness Gap") -> #REF!
A7: Review Required | B7: =COUNTIF(#REF!,"Review Required") -> #REF!

Sheet Test Cases
A1: Test ID | B1: Scenario | C1: Expected | D1: Actual (formula) | E1: Pass/Fail (manual)
A2: T01 | B2: All 65 questions answered — completion = 100% | C2: 100% | D2: =TEXT(Dashboard!B4,"0%") -> 100% | E2: PASS
A3: T02 | B3: Hidden Score populates (1–5) for all scored responses | C3: 65 | D3: =COUNTA(#REF!) -> 1 | E3: PASS
A4: T03 | B4: Not Sure excluded from average (5 Not Sure, rest score-3) | C4: 3 | D4: actual=155 | E4: PASS
A5: T04 | B5: Not Applicable excluded from average (5 N/A, rest score-3) | C5: 3 | D5: actual=1085 | E5: PASS
A6: T05 | B6: Completion % = 30/65 when 30 answered | C6: 46% | D6: actual=930 | E6: PASS
A7: T06a | B7: GOV domain avg = 2 when all GOV set to score-2 | C7: 2 | D7: =IFERROR(ROUND(AVERAGEIFS(#REF!,#REF!,"AI Council Governance and Framework Charter"),0),"") | E7: See notes
A8: T06b | B8: STR domain avg = 4 when all STR set to score-4 | C8: 4 | D8: =IFERROR(ROUND(AVERAGEIFS(#REF!,#REF!,"AI Strategy and Roadmap"),0),"") | E8: See notes
A9: T06c | B9: RAI domain avg = 3 when all RAI set to score-3 | C9: 3 | D9: =IFERROR(ROUND(AVERAGEIFS(#REF!,#REF!,"Responsible AI Guidelines"),0),"") | E9: See notes
A10: T06d | B10: PMF domain avg = 5 when all PMF set to score-5 | C10: 5 | D10: =IFERROR(ROUND(AVERAGEIFS(#REF!,#REF!,"Performance Measurement Framework"),0),"") | E10: See notes
A11: T07 | B11: Dashboard overall avg ~3.5 (GOV=2×18, STR=4×15, RAI=3×16, PMF=5×16) | C11: 3.5 | D11: sample==_Dropdowns!$A$2:$A$8 | E11: PASS
A12: T08 | B12: Recommendations Output has rows when responses set | C12: >=1 row | D12: formula==IFERROR(XLOOKUP($A2&"|"&$J2,'Response Mapping'!$C$2:$C$1086,'Response Mapping'! | E12: PASS
A13: T09 | B13: Gap Flags populate for all answered rows | C13: >=1 flag | D13: formula==IF($K2="","",IF($K2>=4,"Yes","No")) | E13: PASS
A14: T13 | B14: Evidence Required = Yes for score >=4 | C14: Yes | D14: A2='Governance Gap', B2==COUNTIF(tbl_Survey[Gap Flag],"Governance Gap") | E14: PASS
A15: T14 | B15: Blank responses: Dashboard shows blank/0% without errors | C15: 0% | D15: value=GOV-001|No clear executive owner exists for AI | E15: PASS
A16: T15 | B16: Changing a response updates Score, Flag, Rec ID, Dashboard | C16: Verified | D16: found=1/Governance Gap | E16: PASS
A18: NOTE: T10/T11 (formula error scan) require LibreOffice headless — not installed. Verify in Excel. T12 (dropdown arrow) requires manual verification in Excel.

Sheet Glossary
A1: Term | B1: Definition
A2: AI Council | B2: A cross-functional governance body responsible for overseeing AI strategy, risk, and policy across the enterprise.
A3: Governance Gap | B3: A scoring flag indicating the organization lacks a formal control, policy, or accountability structure for the assessed capability.
A4: Mature Capability | B4: A scoring flag indicating a named capability is formally established and consistently applied enterprise-wide.
A5: Optimized Capability | B5: A scoring flag indicating a capability is continuously improved, measured by KPIs, and embedded in the operating model.
A6: Partial Capability | B6: A scoring flag indicating a capability exists in limited or inconsistent form and needs further development.
A7: Responsible AI | B7: Practices ensuring AI systems are fair, transparent, accountable, safe, and compliant with ethical and regulatory standards.
A8: Risk Tier | B8: A classification of an AI use case's potential harm level, used to determine required governance controls and review rigor.
A9: Shadow AI | B9: Unsanctioned use of AI tools by employees outside of official IT and governance processes, creating unknown risk exposure.
A10: Model Card | B10: A standardized documentation artifact describing an AI model's purpose, training data, performance, limitations, and intended use.
A11: NIST AI RMF | B11: The NIST Artificial Intelligence Risk Management Framework — a voluntary framework for managing AI risks across the AI lifecycle.
A12: ISO/IEC 42001 | B12: The international standard for AI management systems, specifying requirements for responsible development and use of AI.
... A21: Time-to-Value | B21: The elapsed time from AI project initiation to the point where measurable business value is realized by the organization.

Sheet AIA-UI-Config
A1: Role Selector
A2: Executive
A3: Governance/Risk/Compliance
A4: Engineering/Delivery
A5: IT/Architecture
A6: Data/Analytics
A7: Business
A8: Workforce/End User

Sheet AIA-Question-Config
A1: Question ID | B1: Role | C1: Domain | D1: Subsection | E1: Subsection Goal | F1: Subsection Weight | G1: Question
A2: GOV-001 | B2: Executive | C2: AI Council Governance and Framework Charter | D2: The AI Council (Structure & Authority) | G2: Which best describes executive accountability for AI in your organization?
A3: GOV-002 | B3: Governance/Risk/Compliance | C3: AI Council Governance and Framework Charter | D3: The AI Council (Structure & Authority) | G3: Which best describes the cross-functional representation of your AI governance council or equivalent decision-making body?
A4: GOV-003 | B4: Governance/Risk/Compliance | C4: AI Council Governance and Framework Charter | D4: The AI Council (Structure & Authority) | G4: Which best describes the authority of your AI governance council to approve, pause, or stop AI initiatives based on risk?
A5: GOV-004 | B5: Governance/Risk/Compliance | C5: AI Council Governance and Framework Charter | D5: The AI Council (Structure & Authority) | G5: Which best describes the meeting cadence and responsiveness of your AI governance council or review process?
A6: GOV-005 | B6: Governance/Risk/Compliance | C6: AI Council Governance and Framework Charter | D6: The AI Council (Structure & Authority) | G6: Which best describes how AI risk disagreements are escalated and resolved?
A7: GOV-006 | B7: Governance/Risk/Compliance | C7: AI Council Governance and Framework Charter | D7: Governance Framework (Policies & Standards) | G7: Which best describes your organization's process for classifying AI use cases by risk level?
A8: GOV-007 | B8: Governance/Risk/Compliance | C8: AI Council Governance and Framework Charter | D8: Governance Framework (Policies & Standards) | G8: Which best describes how your organization defines and measures Responsible AI principles such as fairness, transparency, explainability, privacy, and safety?
A9: GOV-008 | B9: Governance/Risk/Compliance | C9: AI Council Governance and Framework Charter | D9: Governance Framework (Policies & Standards) | G9: Which best describes your organization's policy and controls for employee use of public or unapproved AI tools?
A10: GOV-009 | B10: Engineering/Delivery | C10: AI Council Governance and Framework Charter | D10: Governance Framework (Policies & Standards) | G10: Which best describes the documentation required before an AI solution is approved for deployment?
A11: GOV-010 | B11: Governance/Risk/Compliance | C11: AI Council Governance and Framework Charter | D11: Governance Framework (Policies & Standards) | G11: Which best describes how your AI governance framework aligns to current and emerging AI regulations, standards, and risk management frameworks?
A12: GOV-011 | B12: Governance/Risk/Compliance | C12: AI Council Governance and Framework Charter | D12: Operational Gaps (Implementation) | G12: Which best describes your organization's ability to inventory and track all AI models and AI-enabled vendor capabilities in use?
A13: GOV-012 | B13: Governance/Risk/Compliance | C13: AI Council Governance and Framework Charter | D13: Operational Gaps (Implementation) | G13: Which best describes your organization's approach to assessing and managing risk for vendor-supplied AI tools and AI-enabled products?
... A156: RAC-015 | B156: IT/Architecture | C156: RACI Matrix | D156: Communication & Awareness (The "Informed") | G156: Which best describes who is informed and responsible when an underlying AI vendor releases an API or model change?

Sheet AIA-Question-Response-Map
A1: Question ID | B1: Response 1 | C1: Response 2 | D1: Response 3 | E1: Response 4 | F1: Response 5 | G1: Response 6 | H1: Response 7
A2: GOV-001 | B2: No clear executive owner exists for AI | C2: AI accountability is informal or distributed across multiple leaders without a clear decision owner | D2: A senior leader or function owns AI strategy, but authority, funding, or decision rights are limited | E2: A named executive owns enterprise AI strategy, governance, funding, and prioritization | F2: A named executive owns AI accountability and is supported by formal governance, KPIs, risk oversight, and enterprise-wide operating model integration | G2: Not sure | H2: Not applicable
A3: GOV-002 | B3: No AI governance council or equivalent decision-making body exists | C3: AI governance is primarily IT-led, with limited business, legal, HR, risk, or ethics involvement | D3: The governance body includes some non-technical representation, but participation is inconsistent or decision rights are unclear | E3: The governance body includes consistent representation from IT, business units, legal, security/risk, HR, and data/analytics, with defined roles and decision rights | F3: The governance body is fully cross-functional, has formal authority, includes technical and non-technical stakeholders, and regularly adjusts membership based on AI portfolio needs | G3: Not sure | H3: Not applicable
A4: GOV-003 | B4: No formal AI governance authority exists to review or stop AI initiatives | C4: The council or review group may provide informal guidance, but cannot formally approve, pause, or stop projects | D4: The council can review AI initiatives, but its authority to enforce decisions is unclear or inconsistently applied | E4: The council has documented authority to approve, pause, escalate, or stop AI initiatives based on defined risk criteria | F4: The council has formal decision rights, escalation authority, auditability, and enforcement mechanisms integrated into funding, delivery, and production release processes | G4: Not sure | H4: Not applicable
A5: GOV-004 | B5: No recurring AI governance meeting or review cadence exists | C5: AI governance discussions occur only as needed or after issues arise | D5: The council meets periodically, but the cadence is not always sufficient to support timely AI review and approval | E5: The council meets on a defined schedule with a clear intake process, agenda, and service-level expectations for reviews | F5: The council has a structured cadence, rapid review paths for lower-risk use cases, escalation paths for high-risk use cases, and regularly adjusts cadence based on portfolio demand | G5: Not sure | H5: Not applicable
A6: GOV-005 | B6: No defined escalation path exists for AI risk disagreements | C6: Disagreements are handled informally between teams, with no documented tie-breaking authority | D6: An escalation path exists in practice, but it is not consistently documented or understood by stakeholders | E6: A documented escalation path defines who makes final decisions when teams disagree on AI risk level or approval status | F6: Escalation paths, decision rights, risk ownership, audit trails, and executive tie-breaking authority are formally embedded into the AI governance process | G6: Not sure | H6: Not applicable
A7: GOV-006 | B7: No formal risk tiering system exists for AI use cases | C7: AI risk is considered informally, but there is no consistent rubric or classification process | D7: A basic risk classification approach exists, but criteria or oversight requirements are inconsistently applied | E7: AI use cases are classified into defined risk tiers, and each tier triggers specific review, approval, documentation, and oversight requirements | F7: AI risk tiering is standardized, documented, auditable, aligned to regulatory frameworks, and integrated into intake, delivery, vendor review, monitoring, and production release processes | G7: Not sure | H7: Not applicable
A8: GOV-007 | B8: Responsible AI principles are not formally defined | C8: Responsible AI principles are discussed in general terms, but are not documented or measured | D8: Responsible AI principles are documented, but technical metrics, thresholds, or testing expectations are limited or inconsistent | E8: Responsible AI principles are documented and supported by defined testing practices, review criteria, and measurable thresholds where applicable | F8: Responsible AI standards are measurable, auditable, embedded into delivery and monitoring processes, and tailored by use case risk level and regulatory context | G8: Not sure | H8: Not applicable
A9: GOV-008 | B9: No policy or guidance exists for employee use of public or unapproved AI tools | C9: Informal guidance exists, but employees may still use public AI tools without clear rules or oversight | D9: A policy exists, but communication, enforcement, approved alternatives, or monitoring are limited | E9: A documented policy defines acceptable and prohibited AI use, approved tools, data handling rules, and employee responsibilities | F9: Shadow AI is actively managed through policy, training, approved enterprise tools, monitoring, exception handling, and periodic compliance review | G9: Not sure | H9: Not applicable
A10: GOV-009 | B10: No standard AI documentation is required before deployment | C10: Documentation is created inconsistently and varies by team or project | D10: A standard template exists, but completion, review, or enforcement is inconsistent | E10: AI solutions require standard documentation before deployment, such as model cards, AI fact sheets, risk assessments, data descriptions, and approval records | F10: AI documentation is standardized, reviewed, version-controlled, auditable, tied to risk tiering, and maintained throughout the solution lifecycle | G10: Not sure | H10: Not applicable
A11: GOV-010 | B11: AI governance is not mapped to external regulations, standards, or risk frameworks | C11: The organization is aware of AI regulations and frameworks, but alignment is informal or not documented | D11: Some AI policies or controls reference external frameworks, but coverage is incomplete or inconsistently maintained | E11: AI governance is mapped to relevant frameworks or regulations, such as NIST AI RMF, ISO/IEC 42001, industry requirements, or applicable laws | F11: Regulatory and standards alignment is actively maintained, audited, assigned to control owners, and integrated into governance, risk tiering, vendor review, and delivery processes | G11: Not sure | H11: Not applicable
A12: GOV-011 | B12: No central inventory of AI models or AI-enabled tools exists | C12: Some teams maintain local lists of their own models, but there is no enterprise-wide view | D12: A central inventory exists, but it is incomplete, manually maintained, or omits embedded vendor AI capabilities | E12: A maintained central inventory captures internally built models, fine-tuned models, and AI-enabled vendor capabilities, with assigned owners and basic metadata | F12: The AI inventory is authoritative, integrated with procurement, risk tiering, monitoring, and the change management process, and is reviewed on a defined cadence | G12: Not sure | H12: Not applicable
... A156: RAC-015 | B156: No one is notified or responsible when vendor models change; breaking changes are discovered after impact | C156: Some informal monitoring of vendor changes happens, but no defined RACI | D156: A process exists but coverage of vendors or response time is inconsistent | E156: The RACI defines who is Informed and Responsible for vendor model changes, with a documented process for evaluating impact | F156: Vendor change awareness is automated, integrated with regression testing, supports rapid response to breaking changes, and feeds vendor risk management | G156: Not sure | H156: Not applicable

Sheet AIA-Response-Capture
A1: Respondent Role | B1: Question ID | C1: Chosen Response | D1: Question Score | E1: Subsection Weighted Score | F1: Gap Falg | G1: Recommendation ID | H1: NIST AI RMF Mapping | I1: ISO 42001 Mapping

Sheet _Dropdowns
A1: GOV-001 | B1: GOV-002 | C1: GOV-003 | D1: GOV-004 | E1: GOV-005 | F1: GOV-006 | G1: GOV-007 | H1: GOV-008 | I1: GOV-009 | J1: GOV-010 | K1: GOV-011 | L1: GOV-012 | M1: GOV-013 | N1: GOV-014 | O1: GOV-015 | P1: GOV-016 | Q1: GOV-017 | R1: GOV-018 | S1: STR-001 | T1: STR-002 | U1: STR-003 | V1: STR-004 | W1: STR-005 | X1: STR-006 | Y1: STR-007 | Z1: STR-008 | AA1: STR-009 | AB1: STR-010 | AC1: STR-011 | AD1: STR-012 | AE1: STR-013 | AF1: STR-014 | AG1: STR-015 | AH1: RAI-001 | AI1: RAI-002 | AJ1: RAI-003 | AK1: RAI-004 | AL1: RAI-005 | AM1: RAI-006 | AN1: RAI-007 | AO1: RAI-008 | AP1: RAI-009 | AQ1: RAI-010 | AR1: RAI-011 | AS1: RAI-012 | AT1: RAI-013 | AU1: RAI-014 | AV1: RAI-015 | AW1: RAI-016 | AX1: PMF-001 | AY1: PMF-002 | AZ1: PMF-003 | BA1: PMF-004 | BB1: PMF-005 | BC1: PMF-006 | BD1: PMF-007 | BE1: PMF-008 | BF1: PMF-009 | BG1: PMF-010 | BH1: PMF-011 | BI1: PMF-012 | BJ1: PMF-013 | BK1: PMF-014 | BL1: PMF-015 | BM1: PMF-016 | BN1: AOM-001 | BO1: AOM-002 | BP1: AOM-003 | BQ1: AOM-004 | BR1: AOM-005 | BS1: AOM-006 | BT1: AOM-007 | BU1: AOM-008 | BV1: AOM-009 | BW1: AOM-010 | BX1: AOM-011 | BY1: AOM-012 | BZ1: AOM-013 | CA1: AOM-014 | CB1: AOM-015 | CC1: UCP-001 | CD1: UCP-002 | CE1: UCP-003 | CF1: UCP-004 | CG1: UCP-005 | CH1: UCP-006 | CI1: UCP-007 | CJ1: UCP-008 | CK1: UCP-009 | CL1: UCP-010 | CM1: UCP-011 | CN1: UCP-012 | CO1: UCP-013 | CP1: UCP-014 | CQ1: TRN-001 | CR1: TRN-002 | CS1: TRN-003 | CT1: TRN-004 | CU1: TRN-005 | CV1: TRN-006 | CW1: TRN-007 | CX1: TRN-008 | CY1: TRN-009 | CZ1: TRN-010 | DA1: TRN-011 | DB1: TRN-012 | DC1: TRN-013 | DD1: TRN-014 | DE1: CMA-001 | DF1: CMA-002 | DG1: CMA-003 | DH1: CMA-004 | DI1: CMA-005 | DJ1: CMA-006 | DK1: CMA-007 | DL1: CMA-008 | DM1: CMA-009 | DN1: CMA-010 | DO1: CMA-011 | DP1: CMA-012 | DQ1: CMA-013 | DR1: CMA-014 | DS1: CMA-015 | DT1: CMA-016 | DU1: TAG-001 | DV1: TAG-002 | DW1: TAG-003 | DX1: TAG-004 | DY1: TAG-005 | DZ1: TAG-006 | EA1: TAG-007 | EB1: TAG-008 | EC1: TAG-009 | ED1: TAG-010 | EE1: TAG-011 | EF1: TAG-012 | EG1: TAG-013 | EH1: TAG-014 | EI1: TAG-015 | EJ1: TAG-016 | EK1: RAC-001 | EL1: RAC-002 | EM1: RAC-003 | EN1: RAC-004 | EO1: RAC-005 | EP1: RAC-006 | EQ1: RAC-007 | ER1: RAC-008 | ES1: RAC-009 | ET1: RAC-010 | EU1: RAC-011 | EV1: RAC-012 | EW1: RAC-013 | EX1: RAC-014 | EY1: RAC-015
A2: No clear executive owner exists for AI | B2: No AI governance council or equivalent decision-making body exists | C2: No formal AI governance authority exists to review or stop AI initiatives | D2: No recurring AI governance meeting or review cadence exists | E2: No defined escalation path exists for AI risk disagreements | F2: No formal risk tiering system exists for AI use cases | G2: Responsible AI principles are not formally defined | H2: No policy or guidance exists for employee use of public or unapproved AI tools | I2: No standard AI documentation is required before deployment | J2: AI governance is not mapped to external regulations, standards, or risk frameworks | K2: No central inventory of AI models or AI-enabled tools exists | L2: Vendor AI is not assessed for AI-specific risks during procurement | M2: AI models are not actively monitored after deployment | N2: No AI-specific incident response plan exists | O2: No dedicated budget, people, or tools are allocated to AI governance | P2: The board and senior leaders have limited AI awareness and rarely discuss AI strategy or risk | Q2: Performance and incentives reward only speed to market or delivery; governance compliance plays no role | R2: No channel exists for employees to raise AI safety, bias, or ethics concerns | S2: AI initiatives are not connected to specific business KPIs or outcomes | T2: No framework exists; sourcing decisions are made ad-hoc per project | U2: AI investments are not framed in competitive terms; they are pursued opportunistically | V2: The AI portfolio is not deliberately segmented by internal efficiency vs. external innovation | W2: The AI roadmap assumes data is ready and does not address data debt or readiness | X2: The roadmap is focused on long-term investments only, with no near-term wins, or only short-term pilots, with no long-term plan | Y2: Roadmap interdependencies between platforms and AI initiatives are not mapped | Z2: The AI roadmap is rarely revisited and there is no process to formally stop underperforming projects | AA2: The organization has minimal internal AI expertise and depends on external resources for nearly all AI work | AB2: AI run costs are not forecast; only build costs are considered when funding initiatives | AC2: SMEs are expected to support AI work on top of their day jobs, with no formal time allocation | AD2: No formal plan exists to upskill the workforce on AI tools | AE2: AI success is not formally defined; outcomes are described anecdotally | AF2: There is no defined expectation for when AI initiatives should show value | AG2: AI impact is reported without separating it from other business changes or market shifts | AH2: Fairness is not formally defined for AI use cases | AI2: Training data representativeness is not assessed before models are trained | AJ2: Live AI models are not audited for bias after deployment | AK2: No protocol exists for responding to detected bias in production models | AL2: AI tools are deployed without transparency documentation about intended use and limitations | AM2: The organization cannot provide individual-level explanations of AI decisions | AN2: No process exists for individuals to contest automated AI decisions | AO2: Vendor explainability is not part of procurement evaluation | AP2: AI red-teaming is not performed | AQ2: No drift monitoring or automated alerting exists for AI models | AR2: AI-specific security threats are not addressed; standard application security is assumed sufficient | AS2: No mechanism exists to rapidly disable a misbehaving AI model | AT2: No named individual is accountable for the outputs of AI systems | AU2: Data minimization is not considered when building AI models | AV2: Customer data is used for AI training without checking alignment with consent or terms of service | AW2: AI energy or carbon footprint is not tracked or reported | AX2: AI ROI is not calculated; value is described in qualitative terms only | AY2: Time-to-value is not measured for AI use cases | AZ2: Workforce productivity gains from AI are not measured | BA2: Non-financial value from AI is not tracked | BB2: Model accuracy is judged only by generic benchmarks or vendor claims | BC2: AI response time and throughput are not measured against defined targets | BD2: Hallucination or groundedness in generative AI outputs is not measured | BE2: Concept drift is not measured; retraining decisions are not tied to performance evidence | BF2: Per-query or per-token costs are not tracked | BG2: Compute utilization for AI workloads is not measured | BH2: TCO for AI is not measured; only software and cloud costs are visible | BI2: Energy or carbon metrics are not measured for AI workloads | BJ2: Fairness performance is not reported on a recurring basis to governance | BK2: Human-AI agreement or override rates are not measured | BL2: A complete model performance history could not be produced on request | BM2: Documentation coverage is not measured | BN2: There is no defined operating model for AI; delivery happens wherever a use case originates | BO2: Technical and business ownership are not distinguished; one role is assumed to cover both | BP2: No mechanism exists to discover decentralized or shadow AI usage | BQ2: AI funding is unclear; teams negotiate access to AI capability case by case | BR2: There is no defined intake process for new AI ideas | BS2: HITL requirements are not defined in the AI delivery blueprint | BT2: No process exists for decommissioning AI models; outdated models may remain in production | BU2: When an AI issue arises, no one is sure who owns the fix; accountability has to be negotiated | BV2: There is no AI data supply chain; teams clean and curate data manually for every new project | BW2: There is no live view of production AI models; assembling an inventory takes manual effort | BX2: There are no AI tooling standards; each team picks its own platforms, LLMs, and databases | BY2: Governance guardrails are not part of the AI delivery pipeline | BZ2: New AI roles required by the operating model have not been identified | CA2: Delivery KPIs reward speed only; safety, value realization, and governance are not measured | CB2: No AI literacy program exists for non-technical stakeholders | CC2: AI use cases are prioritized informally; no scoring rubric exists | CD2: Value is defined narrowly (cost savings only); other dimensions are ignored | CE2: Feasibility is estimated as developer hours only; technical complexity factors are not considered | CF2: All "AI ideas" proceed as AI projects; non-AI alternatives are not considered | CG2: Strategic alignment is not factored into AI use case prioritization | CH2: The AI portfolio is not segmented by horizon; everything is incremental | CI2: Approved projects continue to completion regardless of changes in value or context | CJ2: There is no defined way to resolve resource contention; "first one to ask wins" or politics decides | CK2: Privacy and ethics risk is not screened before prioritization; issues are found later in delivery | CL2: Governance cost is not considered in AI use case scoring | CM2: Data sovereignty and IP-leak risk are not reflected in use case scoring | CN2: Use cases are prioritized without a named business champion responsible for adoption | CO2: Change management effort is not part of feasibility scoring | CP2: Lessons from failed AI use cases are not captured or shared | CQ2: Council members do not have a shared baseline of AI fluency | CR2: The council has not been trained on applicable AI regulations or frameworks | CS2: Council has not practiced risk-tiering decisions; calibration is untested | CT2: Council members generally accept model outputs without challenging explainability | CU2: Council members rely entirely on technical team interpretation of AI reports | CV2: Employees do not know which AI tools are sanctioned versus prohibited | CW2: No training exists for prompt engineering or output verification | CX2: Business users cannot consistently identify sensitive data; risk is high | CY2: Users assume AI output is correct by default and do not see themselves as the final filter | CZ2: Business leads cannot reliably distinguish good AI use cases from poor-fit ones; intake is noisy | DA2: Training is one-size-fits-all; no persona differentiation | DB2: AI training content is rarely updated; it does not reflect current AI capabilities or risks | DC2: Training is measured only by completion rates | DD2: Business users do not know how to access AI expertise for grey-area questions | DE2: The AI vision is framed primarily as cost or headcount reduction, generating fear and resistance | DF2: The workforce has no visibility into the AI portfolio | DG2: Personal value of AI is not articulated to end users | DH2: Enterprise AI messaging frequently conflicts with what local leaders say to their teams | DI2: No AI champion network exists; adoption depends entirely on central teams | DJ2: Executives do not visibly use AI tools; AI is positioned as "for everyone else" | DK2: Resistance is not anticipated or mapped; adoption strategies are generic | DL2: No defined channel exists for users to report AI tool problems | DM2: No assessment has been done; the literacy gap is unknown | DN2: Adoption training is generic; functions get the same content regardless of context | DO2: Employees are expected to learn AI tools on top of their existing workload; no protected time exists | DP2: No AI help desk or knowledge base exists for end users | DQ2: Adoption is tracked by licenses assigned only; real usage is unknown | DR2: Performance reviews do not recognize AI use; efficiency-only metrics dominate | DS2: Shadow AI is met with blocking and discipline, with no path to legitimize useful tools | DT2: AI use cases are not revisited after launch; reverting to old processes goes unnoticed | DU2: No standardized hosting strategy exists; AI workloads are deployed wherever teams choose | DV2: No vector database strategy exists; either there is no vector store, or every team builds its own | DW2: Architecture cannot reliably handle concurrent AI inference spikes; core systems are at risk | DX2: The architecture supports only chat-style AI; agentic patterns are not supported | DY2: There is no central model registry; models live on developer machines, notebooks, or scattered storage | DZ2: No centralized gateway exists; AI API calls are made directly from each application | EA2: No process exists for vetting open-source models; either none are allowed, or any model can be used | EB2: Deployment pipelines do not include continuous monitoring; decay is found only by user complaint | EC2: RAG outputs cannot be traced back to their original data sources | ED2: AI is limited to batch data; real-time use cases cannot be supported | EE2: Metadata is inconsistent across data assets; AI models cannot reliably share or interpret data | EF2: No automated detection or masking of sensitive data before AI model calls; reliance is on user discretion | EG2: No automated AI security testing is in place | EH2: AI spend cannot be attributed to specific departments, projects, or use cases | EI2: AI interactions are not consistently logged, or logs are mutable and unreliable for audit | EJ2: The architecture is hard-coupled to a single model provider; switching would require significant rebuild | EK2: No single individual is accountable for any AI model's ethical and legal compliance | EL2: The AI Council has no defined role in the RACI; the framework has no clear owner | EM2: Legal and Privacy are not consulted before AI moves to production | EN2: Run-cost accountability is unassigned; costs become a surprise to whoever notices first | EO2: No one is clearly responsible for verifying training data lineage or right to use | EP2: Model selection happens informally with no documented responsibility | EQ2: No one is clearly responsible for system prompts or safety guardrails in generative AI projects | ER2: Go-live decisions happen ad-hoc, with no defined authority | ES2: No one is clearly responsible for ongoing monitoring; models drift silently | ET2: Accountability for AI incident remediation is unassigned; response is chaotic | EU2: Human reviewers' role is unclear; they may approve outputs without being formally Responsible | EV2: No one is responsible for deciding when AI models are stale; outdated models persist | EW2: Executives receive no structured updates on AI deployments; awareness is anecdotal | EX2: Responsibility for disclosing AI use to end users is not assigned; disclosure may not happen | EY2: No one is notified or responsible when vendor models change; breaking changes are discovered after impact
A3: AI accountability is informal or distributed across multiple leaders without a clear decision owner | B3: AI governance is primarily IT-led, with limited business, legal, HR, risk, or ethics involvement | C3: The council or review group may provide informal guidance, but cannot formally approve, pause, or stop projects | D3: AI governance discussions occur only as needed or after issues arise | E3: Disagreements are handled informally between teams, with no documented tie-breaking authority | F3: AI risk is considered informally, but there is no consistent rubric or classification process | G3: Responsible AI principles are discussed in general terms, but are not documented or measured | H3: Informal guidance exists, but employees may still use public AI tools without clear rules or oversight | I3: Documentation is created inconsistently and varies by team or project | J3: The organization is aware of AI regulations and frameworks, but alignment is informal or not documented | K3: Some teams maintain local lists of their own models, but there is no enterprise-wide view | L3: Procurement reviews vendor AI informally, but there is no required AI risk questionnaire or contract language | M3: Monitoring is informal, ad-hoc, or only happens when an issue is reported | N3: AI incidents would be handled informally or through general IT incident processes, without AI-specific playbooks | O3: Governance work depends on individuals doing it as an "extra" task on top of delivery responsibilities | P3: Leaders receive occasional AI updates, but understanding of differences between predictive AI, generative AI, and agentic AI risks is uneven | Q3: Governance compliance is informally encouraged, but is not part of documented performance measurement | R3: Employees may raise concerns through general channels, but no AI-specific or anonymous option exists | S3: AI initiatives are described in general business terms, but specific KPIs and targets are not consistently defined | T3: Teams make sourcing decisions based on informal preferences, with no documented criteria | U3: AI is being used to keep pace with peers, but differentiated investments are not deliberately identified | V3: One side dominates by default (e.g., all internal productivity, or all customer-facing pilots), with no strategic rationale | W3: Data issues are known but not reflected as milestones, dependencies, or funded work in the roadmap | X3: Some short-term and long-term work exists, but the balance is accidental rather than deliberate | Y3: Dependencies are known informally by individuals, but not documented or used to sequence work | Z3: Roadmap reviews happen ad-hoc; projects continue past their useful life because there is no decision forum | AA3: Some internal AI capability exists, but key roles (e.g., ML engineering, MLOps, data engineering) are heavily dependent on contractors | AB3: Some run costs are estimated, but tracking is inconsistent and budgets do not reflect scaled usage | AC3: SME engagement happens informally, depending on individual availability and goodwill | AD3: Training is delivered ad-hoc at tool launch, with no ongoing curriculum or role-based content | AE3: Success is defined narrowly (e.g., model accuracy only, or pilot completion only), missing adoption or business impact | AF3: Time-to-value expectations are inconsistent and applied unevenly depending on sponsor influence | AG3: Impact is described anecdotally, without controls, baselines, or statistical comparisons | AH3: Fairness is discussed in general terms but not translated into specific definitions per use case | AI3: Teams informally consider data quality, but representativeness across protected or relevant groups is not systematically verified | AJ3: Bias is reviewed only when concerns are raised, not on a defined schedule | AK3: Response would be ad-hoc, decided in the moment, with no playbook for retraining, rollback, or disablement | AL3: Some teams produce informal documentation, but there is no standard model card or transparency note format | AM3: Some teams can produce technical explanations, but they are not translated into plain language for affected users | AN3: Appeals may be handled informally through general customer service channels, with no AI-specific path | AO3: Procurement asks about explainability informally, but no formal disclosure or contract requirement exists | AP3: Informal adversarial testing happens occasionally, with no defined scope, scenarios, or roles | AQ3: Drift is checked manually or only when an issue is reported, with no automated alerts | AR3: Some teams have implemented basic guardrails, but there is no enterprise AI security standard or threat model | AS3: Disablement would be slow or manual, depending on individuals with system access | AT3: Accountability is implied by role but not formally assigned for each AI system | AU3: Teams may consider it informally, but no standard or review process exists | AV3: Consent is considered informally, but there is no documented mapping from training data to consent basis | AW3: Some general cloud or compute usage is tracked, but not attributed to AI workloads | AX3: ROI is estimated informally for some initiatives, with no consistent methodology | AY3: Time-to-value is described anecdotally; there is no consistent definition or tracking | AZ3: Anecdotes suggest productivity gains, but there is no measurement methodology | BA3: Customer or employee experience is tracked generally, but not isolated to AI-driven interactions | BB3: Some teams build informal test sets, but there is no organized ground-truth practice | BC3: Performance is monitored informally; SLAs are not defined or are not tied to customer/business impact | BD3: Output quality is judged anecdotally or by user complaints rather than a measurement methodology | BE3: Retraining happens on calendar cadence, without measured drift signals | BF3: Costs are tracked at an aggregate or invoice level, with no per-use-case or per-query breakdown | BG3: Utilization is checked manually and occasionally; idle capacity is common but not addressed | BH3: Some additional costs are included anecdotally, but no consistent TCO framework is applied | BI3: Sustainability is tracked at the enterprise level but not isolated to AI workloads | BJ3: Some fairness data exists, but it is not aggregated into a recurring scorecard or governance review | BK3: Overrides are captured in logs but not analyzed as a quality signal | BL3: Producing a performance history would take weeks or months and require significant manual effort | BM3: Coverage is estimated informally; no systematic count of documented vs. undocumented models exists | BN3: AI delivery is split across teams ad-hoc, with no clear archetype (Centralized / Decentralized / Federated) | BO3: Ownership is split informally, but responsibilities for model performance vs. business outcome are unclear | BP3: Shadow AI is detected only when it causes a problem; there is no proactive discovery | BQ3: A central AI team exists but funding is ad-hoc, leading to bottlenecks and inconsistent access | BR3: Ideas reach delivery through personal networks rather than a structured intake | BS3: Teams decide HITL on a per-project basis, with no enterprise standards | BT3: Models are retired ad-hoc when problems are noticed, with no standard process | BU3: A RACI exists on paper but the team does not know it; accountability is rediscovered each incident | BV3: Some data pipelines are reused, but most AI projects still rebuild data prep from scratch | BW3: A model list exists but is updated manually and is often out of date | BX3: Some informal preferences exist but are not enforced, leading to growing tooling debt | BY3: Guardrails exist as manual checks at the end of the cycle, often bypassed under deadline pressure | BZ3: Some new role titles are used informally, but job descriptions and accountabilities are not defined | CA3: KPIs include some non-speed measures, but they are informal and inconsistently applied | CB3: Non-technical stakeholders pick up AI knowledge ad-hoc through their own initiative | CC3: Some teams score informally, but criteria and scales differ across the portfolio | CD3: Multiple value dimensions are discussed informally, but only one is used in scoring | CE3: Some complexity factors are considered ad-hoc, but they aren't part of a defined assessment | CF3: Non-AI alternatives are sometimes considered informally, depending on the reviewer | CG3: Strategic alignment is discussed informally, but not reflected in the scoring | CH3: Some Horizon 2/3 ideas exist but never reach funding; the portfolio is overwhelmingly Horizon 1 | CI3: Mid-flight changes are theoretically possible but rarely happen due to political dynamics | CJ3: Resource conflicts are escalated to leadership case by case, with no consistent decision framework | CK3: Some risk discussions happen informally at intake, but they don't influence prioritization decisions | CL3: Governance cost is mentioned anecdotally but not part of the scoring methodology | CM3: These risks are discussed but not scored, often surfacing during delivery | CN3: A champion is named informally but with no accountability for adoption outcomes | CO3: Change management is mentioned but not scored, leading to post-launch adoption failures | CP3: Some informal post-mortems occur, but findings don't influence future prioritization | CQ3: Some council members are AI-literate, but knowledge varies widely | CR3: Regulations are discussed informally, but no structured training has been delivered | CS3: Some informal discussions about past decisions occur, but no calibration exercises | CT3: Some council members ask explainability questions, but skill level is uneven | CU3: Some members spot obvious issues, but most rely on the technical team to flag failures | CV3: Guidance exists but is not widely communicated or remembered | CW3: Some basic prompt training exists, but output verification and ethics are not addressed | CX3: General data classification exists, but AI-specific data risks are not covered | CY3: Accountability is implied but not clearly communicated; some users defer to the AI | CZ3: Some leads have good intuition, but most rely on the central AI team to filter ideas | DA3: A few sessions are role-specific, but most content is generic | DB3: Annual refresh only, with no mechanism for mid-year updates when AI capabilities change rapidly | DC3: Anecdotes suggest training works, but no behavior-change metric is tracked | DD3: Some employees know who to ask, but the path is informal and depends on relationships | DE3: Leaders use both framings inconsistently, sending mixed signals to the workforce | DF3: Some announcements happen when projects launch, but the broader portfolio is opaque | DG3: Generic productivity benefits are mentioned, but not tied to specific roles or pain points | DH3: Some leaders cascade enterprise messaging, but others contradict it based on local priorities | DI3: Some informal champions exist, but no defined role or recognition | DJ3: A few executives use AI privately, but it is not visible to the workforce | DK3: Some informal recognition of resistance exists, but no targeted engagement plan | DL3: Feedback can be raised through general channels, but users hesitate due to perceived blame | DM3: Some functions have informal views of their gap, but no enterprise audit | DN3: Some functions have tailored content, but most still use generic tool training | DO3: Some teams informally allow time for AI learning, depending on the manager | DP3: A general IT help desk handles AI questions ad-hoc, with no AI-specific content | DQ3: Some basic usage data exists, but adoption is not defined in business outcome terms | DR3: Some managers informally reward AI innovators, but this is not part of the review system | DS3: Response is inconsistent and reactive, depending on who discovers it | DT3: Some informal check-ins happen, but no structured review at a defined interval | DU3: Teams use multiple platforms ad-hoc, leading to inconsistent security and operational controls | DV3: Multiple team-owned vector stores have proliferated, creating silos and duplication | DW3: Some isolation exists, but spike handling is reactive and capacity is over-provisioned or under-provisioned | DX3: Some teams are experimenting with agents, but there is no architectural pattern or guardrails | DY3: Some teams maintain local registries, but there is no enterprise standard | DZ3: A partial gateway exists for some use cases, but most calls bypass it | EA3: Teams choose models informally, without consistent vetting for license, security, or quality | EB3: Some models have monitoring, but it is not integrated with deployment pipelines | EC3: Lineage can be reconstructed manually with significant effort, but is not part of the AI architecture | ED3: Real-time data exists for some systems, but AI consumes data primarily through batch processes | EE3: Some data domains have local metadata standards, but there is no enterprise schema | EF3: Some controls exist (e.g., DLP at network layer) but are not AI-specific | EG3: Some manual testing happens occasionally, but no automated tooling | EH3: Aggregate AI spend is visible, but breakdown by department or project is manual and incomplete | EI3: Logs exist but lack retention, immutability, or completeness for compliance purposes | EJ3: Some abstraction exists but switching providers would still require substantial work across applications | EK3: Accountability is held by committees or unclear groups, with no single named individual | EL3: The Council is marked as Consulted only; no role is Accountable for the framework | EM3: Legal/Privacy may be consulted informally, but it is not part of the deployment gate | EN3: Run costs are owned by central IT by default, even when business units drive demand | EO3: Responsibility is assumed by the developer with no governance oversight | EP3: Individual developers choose models with no architecture or governance check | EQ3: Either IT or SMEs do this in isolation, leading to either weak guardrails or weak business context | ER3: The developer or product team self-approves go-live without governance gate | ES3: The original developer is informally responsible but lacks tooling, time, or authority to act | ET3: Accountability is debated during the incident rather than predefined | EU3: Reviewers are marked Informed in practice, with no clear accountability for final output | EV3: Decommissioning happens only when problems are escalated; there is no defined authority | EW3: All AI deployments are reported the same way regardless of risk, leading to noise or blind spots | EX3: Disclosure happens informally on a project-by-project basis, with no consistent standard | EY3: Some informal monitoring of vendor changes happens, but no defined RACI
A4: A senior leader or function owns AI strategy, but authority, funding, or decision rights are limited | B4: The governance body includes some non-technical representation, but participation is inconsistent or decision rights are unclear | C4: The council can review AI initiatives, but its authority to enforce decisions is unclear or inconsistently applied | D4: The council meets periodically, but the cadence is not always sufficient to support timely AI review and approval | E4: An escalation path exists in practice, but it is not consistently documented or understood by stakeholders | F4: A basic risk classification approach exists, but criteria or oversight requirements are inconsistently applied | G4: Responsible AI principles are documented, but technical metrics, thresholds, or testing expectations are limited or inconsistent | H4: A policy exists, but communication, enforcement, approved alternatives, or monitoring are limited | I4: A standard template exists, but completion, review, or enforcement is inconsistent | J4: Some AI policies or controls reference external frameworks, but coverage is incomplete or inconsistently maintained | K4: A central inventory exists, but it is incomplete, manually maintained, or omits embedded vendor AI capabilities | L4: An AI vendor review exists, but coverage of transparency, training data, audit rights, and model updates is inconsistent | M4: Some models are monitored, but coverage, metrics, thresholds, or alerting are inconsistent across the AI portfolio | N4: Some AI incident response procedures exist, but they are incomplete, untested, or not consistently communicated | O4: Some governance resources exist, but funding, staffing, or tooling are inconsistent across the AI portfolio | P4: Leadership receives periodic AI briefings, but coverage of regulation, risk categories, and strategic implications is inconsistent | Q4: Some leaders include governance in performance discussions, but expectations are inconsistent across teams | R4: A channel exists, but it is not widely communicated, lacks anonymity options, or does not have a defined AI triage process | S4: Some AI initiatives have defined KPIs, but value cases vary in rigor across the portfolio | T4: A sourcing guide exists, but it is not consistently applied or doesn't address newer options like fine-tuning, RAG, or agentic patterns | U4: Leadership recognizes both parity and differentiation goals, but the portfolio mix is not deliberately managed | V4: Some balance exists, but it is the result of bottom-up demand rather than a deliberate strategic choice | W4: Some roadmap items include data work, but coverage is inconsistent and downstream AI initiatives are still at risk | X4: A horizon balance is recognized as important, but the roadmap doesn't consistently sequence pilots to support long-term investments | Y4: Some major dependencies are documented, but coverage is inconsistent and surprises still occur during delivery | Z4: The roadmap is reviewed periodically, but stop/continue decisions are inconsistent or politically difficult | AA4: A defined AI talent profile exists, but hiring, retention, and upskilling are inconsistent | AB4: Cost forecasts exist for major initiatives, but coverage is partial and surprises occur as usage scales | AC4: Some initiatives have allocated SME time, but the practice is inconsistent across the portfolio | AD4: A training plan exists for some tools or roles, but coverage and adoption tracking are inconsistent | AE4: Multiple success measures exist, but the balance between technical and business measures is inconsistent across initiatives | AF4: Some AI initiatives have defined ROI windows, but the framework is not portfolio-wide | AG4: Some initiatives use A/B testing or baseline comparisons, but the practice is not consistent across the portfolio | AH4: Some high-stakes use cases have documented fairness definitions, but coverage and rigor are inconsistent | AI4: Some models go through representativeness checks, but standards and coverage are inconsistent | AJ4: Some models are audited periodically, but coverage and remediation expectations are inconsistent | AK4: A response approach exists, but it is informal, inconsistently applied, or untested | AL4: A standard model card or transparency note format exists, but coverage of the live AI portfolio is incomplete | AM4: Plain-language explanations exist for some use cases, but coverage and quality are inconsistent | AN4: An appeal process exists for some use cases, but it is not well-communicated, timely, or consistently applied | AO4: Some procurement decisions evaluate vendor explainability, but the practice is not standardized | AP4: Red-teaming happens for some high-impact use cases, but coverage and rigor are inconsistent | AQ4: Drift monitoring exists for some models, but thresholds, alerting, and ownership are inconsistent | AR4: AI security controls exist for some applications, but coverage of threats like prompt injection, data poisoning, and model extraction is uneven | AS4: Disablement capability exists for some models, but procedures and response times are inconsistent | AT4: Accountable owners are named for some AI systems, but coverage is inconsistent | AU4: Some AI projects apply data minimization, but coverage and rigor are inconsistent | AV4: Some training data has documented consent alignment, but coverage and review are inconsistent | AW4: Some AI workloads have sustainability metrics, but coverage is partial and reporting is inconsistent | AX4: A ROI methodology exists but is applied unevenly, with gaps in cost capture or benefit attribution | AY4: Some initiatives track time-to-value, but definitions and data quality are inconsistent | AZ4: Some AI tools have productivity measures, but coverage and methodology vary | BA4: Some AI touchpoints have experience measurement, but coverage is partial and trends are not consistently reviewed | BB4: Ground-truth datasets exist for some use cases, but coverage, refresh, and rigor are inconsistent | BC4: Some AI services have SLAs and dashboards, but coverage and breach response are inconsistent | BD4: Some generative AI use cases have hallucination metrics, but methodology and coverage are inconsistent | BE4: Some models track drift and trigger retraining, but practices vary across the portfolio | BF4: Some AI services have unit-cost visibility, but alerting for cost spikes is inconsistent or missing | BG4: Some workloads have utilization monitoring, but right-sizing or scaling actions are inconsistent | BH4: TCO is calculated for some initiatives, but human oversight, labeling, and governance costs are inconsistently included | BI4: Some high-scale AI workloads have sustainability measurement, but coverage and methodology are inconsistent | BJ4: A fairness report exists, but cadence, scope, or governance follow-through is inconsistent | BK4: Some use cases analyze agreement rate, but it is not consistently used to drive model improvements | BL4: Performance histories exist for some models, but completeness, retention, and lookup are inconsistent | BM4: Some coverage data exists, but currency (whether documentation reflects the live model) is inconsistent | BN4: An operating-model archetype is recognized in practice, but roles, standards, and decision rights are inconsistent | BO4: Some AI initiatives have defined technical and business owners, but the practice is inconsistent across the portfolio | BP4: Some discovery activities exist (surveys, license reviews) but coverage and follow-through are inconsistent | BQ4: A funding model exists (e.g., chargeback or central pool), but it is not consistently applied or perceived as fair | BR4: An intake process exists, but it does not consistently cover both feasibility and risk, or it is bypassed by some teams | BS4: HITL guidance exists but is not consistently applied; coverage by risk tier or use-case type is incomplete | BT4: A retirement process exists but is inconsistently applied; criteria, disposition, and communication vary | BU4: Some incident types have clear accountability, but coverage and team awareness are inconsistent | BV4: A data supply-chain pattern exists, but reuse, quality SLAs, and ownership are inconsistent | BW4: Some teams maintain live inventories, but enterprise coverage and refresh cadence are inconsistent | BX4: A standard stack is recommended, but exceptions are common and the standards are not consistently maintained | BY4: Some automated guardrails exist (PII filters, basic bias checks) but coverage is inconsistent across teams | BZ4: Some roles are defined, but coverage, leveling, and integration with HR are inconsistent | CA4: Some teams have balanced KPIs, but practice varies across the AI portfolio | CB4: Some training is offered, but coverage by function and depth of content are inconsistent | CC4: A scoring rubric exists, but it is not consistently used or maintained | CD4: A multi-dimensional definition exists, but weighting is inconsistent or contested | CE4: A feasibility rubric exists, but coverage of data readiness, model complexity, and integration is inconsistent | CF4: Intake asks the question, but answers are not always rigorous or acted upon | CG4: Some prioritization decisions reflect strategy, but the weighting is inconsistent across the portfolio | CH4: The portfolio includes multiple horizons, but the balance is unmanaged and shifts with budget cycles | CI4: Some projects are reviewed mid-flight, but the practice is inconsistent and decisions take a long time | CJ4: A resource allocation process exists, but it is not consistently followed when high-pressure projects emerge | CK4: A pre-prioritization risk screening exists but is applied inconsistently | CL4: Governance cost is included for some use cases but not consistently estimated | CM4: Some risk factors are scored, but coverage of third-party LLM and external data risks is uneven | CN4: Champions are named for some use cases, but their responsibility for adoption is inconsistently defined | CO4: Some scoring factors capture change management, but coverage is inconsistent | CP4: Lessons are captured for some failures, but the practice is inconsistent and not always referenced during new intake | CQ4: Baseline AI fluency training has been delivered, but coverage of newer AI categories (generative, agentic) is incomplete | CR4: Some council members received regulatory training, but coverage is inconsistent across members and topics | CS4: Calibration exercises have been run, but coverage and frequency are insufficient | CT4: Council has received explainability training, but applies it inconsistently | CU4: Council training includes failure modes, but application during reviews is inconsistent | CV4: Most employees know the basic rules, but data-handling specifics are not consistently understood | CW4: Training covers both prompting and verification, but depth and adoption are inconsistent | CX4: Some users have AI-specific data training, but coverage and freshness are inconsistent | CY4: Policy states human accountability, but reinforcement through training is inconsistent | CZ4: Training exists but is inconsistently delivered or applied | DA4: Some persona-based paths exist, but coverage of all relevant roles is incomplete | DB4: Updates happen, but cadence and coverage are inconsistent | DC4: Some behavior metrics are tracked, but linkage to training is inconsistent | DD4: A path exists (help desk, office hours), but awareness or response times are inconsistent | DE4: The augmentation framing is articulated, but uneven across leaders and channels | DF4: A communication channel exists, but updates are infrequent or incomplete | DG4: Some use cases include WIIFM messaging, but coverage and specificity vary | DH4: Cascade messaging exists but is not consistently picked up by local leaders | DI4: A champion network exists, but coverage of business units is incomplete | DJ4: Some executive AI use is visible, but it is inconsistent across the leadership team | DK4: Resistance mapping has been done once, but engagement plans are inconsistent or unfunded | DL4: A channel exists, but communication, anonymity, or follow-through are inconsistent | DM4: A literacy audit has been started, but coverage or methodology is incomplete | DN4: Function-specific paths exist for some areas, but coverage is incomplete | DO4: A policy exists but is inconsistently applied across teams | DP4: An AI knowledge base exists but content is sparse or out of date | DQ4: A small number of adoption KPIs exist, but coverage and consistency are inconsistent | DR4: Performance reviews mention AI, but criteria are vague or inconsistently applied | DS4: A "understand-and-govern" approach is the policy, but in practice teams still default to blocking | DT4: Some use cases are reviewed, but coverage and rigor are inconsistent | DU4: A hosting strategy is documented, but adoption is partial and exceptions are common | DV4: A centralized option exists, but adoption is partial and many teams still spin up their own | DW4: Capacity is planned for some workloads, but the architecture doesn't consistently scale or isolate AI traffic | DX4: An agent pattern is emerging, but governance, tool registration, and observability are incomplete | DY4: A central registry exists, but coverage and metadata completeness are inconsistent | DZ4: A gateway is in place but lacks consistent safety filtering, cost attribution, or routing logic | EA4: A vetting process exists, but coverage of licensing, security, performance, and lifecycle is incomplete | EB4: Some pipelines include monitoring, but coverage and metrics are inconsistent | EC4: Lineage exists for some AI use cases, but coverage and granularity are inconsistent | ED4: Some AI use cases consume real-time data, but the architecture isn't uniformly capable | EE4: A metadata standard exists, but coverage of in-scope AI data assets is incomplete | EF4: Detection and masking exist for some use cases, but coverage and accuracy are inconsistent | EG4: Automated tools are in place for some endpoints, but coverage and frequency are inconsistent | EH4: Cost attribution exists for some workloads, but accuracy and coverage are inconsistent | EI4: Logs are kept for some AI systems, but coverage and immutability are inconsistent | EJ4: A model abstraction layer exists, but it has gaps for newer capabilities or evaluation/observability | EK4: Some AI models have a named accountable owner, but coverage is inconsistent | EL4: Framework accountability is implied but not clearly documented in the RACI | EM4: Legal/Privacy consultation is required but inconsistently applied across teams or risk tiers | EN4: Some AI solutions have clear run-cost ownership, but practice is inconsistent | EO4: Responsibility exists but is split unclearly between Data Governance and Data Engineering, leading to confusion | EP4: A standard exists for model selection, but Responsible and Accountable parties are not consistently followed | EQ4: Responsibility is shared in practice, but the RACI is unclear about who has Accountability | ER4: A go-live authority is defined, but the gate is inconsistently enforced | ES4: Responsibility is assigned but inconsistent across teams (some MLOps-led, some developer-led) | ET4: Accountability is defined but coverage of incident types or escalation steps is incomplete | EU4: Reviewer role is defined but inconsistently applied across HITL use cases | EV4: Authority is defined but inconsistently applied across the AI portfolio | EW4: Risk-tier-based reporting exists but is inconsistent or doesn't reach the right leaders | EX4: Disclosure is required but ownership is unclear or coverage is incomplete | EY4: A process exists but coverage of vendors or response time is inconsistent
A5: A named executive owns enterprise AI strategy, governance, funding, and prioritization | B5: The governance body includes consistent representation from IT, business units, legal, security/risk, HR, and data/analytics, with defined roles and decision rights | C5: The council has documented authority to approve, pause, escalate, or stop AI initiatives based on defined risk criteria | D5: The council meets on a defined schedule with a clear intake process, agenda, and service-level expectations for reviews | E5: A documented escalation path defines who makes final decisions when teams disagree on AI risk level or approval status | F5: AI use cases are classified into defined risk tiers, and each tier triggers specific review, approval, documentation, and oversight requirements | G5: Responsible AI principles are documented and supported by defined testing practices, review criteria, and measurable thresholds where applicable | H5: A documented policy defines acceptable and prohibited AI use, approved tools, data handling rules, and employee responsibilities | I5: AI solutions require standard documentation before deployment, such as model cards, AI fact sheets, risk assessments, data descriptions, and approval records | J5: AI governance is mapped to relevant frameworks or regulations, such as NIST AI RMF, ISO/IEC 42001, industry requirements, or applicable laws | K5: A maintained central inventory captures internally built models, fine-tuned models, and AI-enabled vendor capabilities, with assigned owners and basic metadata | L5: Vendor AI is subject to a defined AI risk assessment, with documented contract requirements for transparency, model documentation, change notification, and audit or attestation rights | M5: Production AI models are monitored against defined metrics for performance, drift, and bias, with alerting and assigned owners for response | N5: A documented AI incident response plan defines triage, model disable procedures, communications, regulator notification triggers, and post-incident review | O5: Governance is funded with dedicated headcount, tooling, and a defined operating budget that scales with the AI portfolio | P5: Board and senior executives receive structured AI literacy programming covering strategy, risk types, regulation, and business implications | Q5: Governance and Responsible AI compliance are documented expectations in performance reviews, OKRs, or delivery scorecards for relevant roles | R5: A documented, communicated channel allows employees to raise AI concerns, including anonymously, with a defined triage and response process | S5: Each major AI initiative has a documented business case, named KPI, baseline, target, and accountable owner | T5: A documented buy/build/tune framework considers cost, risk, differentiation, time-to-value, and vendor lock-in, and is consistently applied | U5: The AI portfolio is intentionally balanced between competitive parity investments and differentiated, defensible AI capabilities | V5: The AI portfolio has a defined target mix between internal efficiency and customer-facing innovation, reviewed at the leadership level | W5: The AI roadmap explicitly sequences data readiness milestones (quality, accessibility, governance, vector/feature infrastructure) ahead of dependent AI initiatives | X5: The roadmap is deliberately structured into near-term, medium-term, and long-term horizons, with quick wins selected to build trust and capability for larger bets | Y5: Roadmap dependencies are documented, used to sequence work, and reviewed during planning and prioritization | Z5: The roadmap is reviewed on a defined cadence with documented stage-gate criteria for continuing, pivoting, or stopping initiatives | AA5: The organization has a documented AI talent strategy with role definitions, hiring plans, upskilling pathways, and retention practices | AB5: AI run costs are forecast per use case, tracked against budget, and reflected in funding and architecture decisions | AC5: SME time is explicitly planned, funded, and protected for AI initiatives through agreements with their primary leaders | AD5: A documented workforce AI enablement plan covers role-based training, communications, and adoption measurement for each major AI tool | AE5: Each AI initiative defines success across both technical performance and business adoption or outcome metrics | AF5: AI initiatives have defined time-to-value windows aligned to initiative type (e.g., pilot vs. platform vs. strategic bet) | AG5: AI initiatives use defined attribution methods (A/B tests, holdouts, baselines, or counterfactuals) suited to the use case | AH5: High-stakes AI use cases have documented fairness definitions (e.g., demographic parity, equal opportunity, predictive parity) chosen based on use case context | AI5: Training data is reviewed for representativeness and coverage gaps against defined population segments before model approval | AJ5: High-risk AI models are audited for bias on a defined cadence, with documented thresholds and remediation steps | AK5: A documented protocol defines remediation paths (retraining, weight adjustment, rollback, disablement) and decision rights when bias is detected | AL5: All high-impact AI tools have a completed model card or transparency note covering intended use, limitations, training data, and contact for concerns | AM5: High-impact AI decisions include documented, plain-language explanations accessible to affected users on request | AN5: A documented appeal process exists for AI-driven decisions, including how to request human review, expected response times, and how to access decision rationale | AO5: Vendor AI procurement requires documented disclosure of explainability capabilities, limitations, and intended-use guidance | AP5: A defined red-teaming program tests high-impact AI for harmful output, bias, jailbreaks, and misuse, with documented scenarios and remediation expectations | AQ5: Production AI models have automated drift monitoring against defined thresholds, with alerts routed to assigned owners | AR5: A defined AI security architecture addresses AI-specific threats with input/output guardrails, training-data integrity controls, and AI-aware monitoring | AS5: High-impact AI models have documented kill-switch procedures with defined authority, technical means, and target response times | AT5: Each AI system has a named accountable owner with documented responsibilities for performance, risk, and incident response | AU5: AI projects apply documented data minimization principles, with privacy review before training and deployment | AV5: Training data sources are mapped to consent or legal basis, with privacy review required before use | AW5: AI energy or carbon footprint is tracked for major training and inference workloads and included in periodic reporting | AX5: AI initiatives use a documented ROI methodology covering build cost, run cost, value lift, and risk-adjusted returns | AY5: A defined time-to-value metric is tracked across the AI portfolio, with stage definitions (pilot, production, value-realized) | AZ5: AI productivity is measured for major tools using a defined methodology, including time-saved and reinvestment outcomes | BA5: Major AI-driven interactions have defined experience metrics (e.g., CSAT, NPS, ease-of-use) tracked over time | BB5: High-impact AI use cases have curated ground-truth datasets used for pre-deployment evaluation and ongoing performance measurement | BC5: Customer-facing AI services have defined SLAs for latency and throughput, with dashboards and breach response procedures | BD5: Generative AI use cases use defined metrics for hallucination and groundedness, with thresholds and evaluation procedures | BE5: Production models have defined drift metrics with thresholds that trigger documented retraining or replacement workflows | BF5: Unit costs are tracked per use case with defined alert thresholds for unexpected spikes | BG5: Compute utilization is monitored for AI workloads, with right-sizing and scaling actions taken based on observed patterns | BH5: AI TCO is calculated using a defined framework that includes software, infrastructure, data, oversight, governance, and audit costs | BI5: High-scale AI deployments have defined energy or carbon metrics, tracked and reported on a defined cadence | BJ5: A fairness scorecard is produced on a defined cadence (e.g., quarterly) covering high-risk AI models, with documented governance review | BK5: High-impact AI use cases measure agreement rate as a defined quality signal, with thresholds for review | BL5: Performance histories are maintained for in-scope AI models and can be produced within defined time targets on request | BM5: Documentation coverage and currency are tracked across the AI portfolio, with defined targets and remediation when coverage drops | BN5: A documented operating-model archetype (Centralized, Decentralized, or Federated) defines how AI is delivered, with clear roles and standards | BO5: AI initiatives have named technical owners (for model performance) and business owners (for outcome), with documented responsibilities | BP5: A defined process discovers shadow AI through periodic surveys, SaaS monitoring, or expense analysis, with a path to bring tools into governance | BQ5: AI funding is governed by a documented model (central pool, chargeback, federated, or hybrid) with clear access and prioritization rules | BR5: A single intake process vets new AI ideas for feasibility (strategy) and risk (governance), with clear ownership and timelines | BS5: The AI blueprint defines HITL requirements by use-case type and risk tier, with documented points of intervention, approval, and override | BT5: A documented decommissioning protocol defines retirement criteria, data and artifact disposition, user communications, and approvals | BU5: Day-to-day teams can name the accountable owner for common AI issues (bias, outage, drift) without checking a document | BV5: A documented AI data supply chain delivers curated, quality-checked data to AI projects through reusable pipelines or a feature store | BW5: A central dashboard shows status, version, and risk tier of production AI models, refreshed on a defined cadence | BX5: A documented AI tool stack defines preferred LLMs, vector databases, monitoring, and orchestration platforms, with an exception process | BY5: Automated guardrails (PII, bias, safety, evaluation thresholds) are embedded in the AI CI/CD pipeline and block deployment on failure | BZ5: Required AI roles are defined with job descriptions, leveling, and ownership in the operating model | CA5: AI delivery teams have documented KPIs that include safe deployment, value realization, and governance compliance | CB5: A literacy program covers Legal, HR, Finance, and Compliance stakeholders involved in AI approvals, with content tailored to each function | CC5: A documented scoring rubric (value + feasibility) is applied to every candidate use case before prioritization | CD5: Value is defined across multiple dimensions (cost savings, revenue, customer experience, risk mitigation) with documented weighting | CE5: Feasibility scoring includes data readiness, model complexity, integration burden, and run cost as documented factors | CF5: Intake requires an explicit non-AI-alternative check, and use cases are redirected to simpler solutions when appropriate | CG5: The prioritization framework applies an explicit multiplier or weighting for use cases that map to top enterprise strategic priorities | CH5: The portfolio has a target mix across Horizons 1, 2, and 3, reviewed by executive leadership on a defined cadence | CI5: A defined stage-gate or portfolio review process can de-prioritize or stop in-flight projects when their scores drop or context changes | CJ5: Documented criteria (value score, strategic alignment, sequencing dependencies) resolve contention between projects competing for the same resources | CK5: Privacy and ethics risk is screened at the prioritization stage, with risk levels influencing scoring and approval | CL5: Governance cost (audit, testing, legal review, monitoring) is included in the use case score using a documented method | CM5: Use case scoring includes data sovereignty, vendor data handling, and IP-leak risk where third-party LLMs or external data are in scope | CN5: Every prioritized AI use case has a named business champion with documented responsibility for adoption | CO5: Feasibility scoring explicitly captures training need, cultural resistance, and workflow change effort | CP5: Failed and de-prioritized use cases are documented in a shared library and reviewed during new use case intake | CQ5: Council members complete fluency training covering predictive, generative, and agentic AI and their distinct risk profiles | CR5: Council members complete training on applicable AI regulations and frameworks (EU AI Act, NIST AI RMF, industry-specific) | CS5: Council members practice risk-tiering through documented scenario exercises that test consistency of judgment | CT5: Council members can identify when a model is opaque and ask defined questions about training data, features, and decision logic | CU5: Council members can recognize hallucinations, drift, and bias signals in AI reports without solely relying on technical team interpretation | CV5: Employees complete training that clearly identifies sanctioned and prohibited AI tools and acceptable data uses | CW5: Training covers prompt engineering, output verification, fact-checking, and bias awareness for AI-generated content | CX5: Business users complete training on identifying sensitive data and its appropriate use in AI contexts (training, fine-tuning, grounding) | CY5: Users complete training that clearly establishes their accountability for the final work product when using AI | CZ5: Business leads complete training that helps them distinguish good vs. poor-fit AI use cases before submitting them for intake | DA5: The AI training program has distinct learning paths for each major persona (general staff, managers, developers, council) | DB5: Training content is refreshed on a defined cadence (e.g., quarterly) with an owner accountable for currency | DC5: Training impact is measured through behavior-change indicators (incident rates, shadow-AI declines, adoption metrics) | DD5: A defined channel (help desk, office hours, named experts) is available and known to business users for AI questions | DE5: Leadership consistently articulates an AI vision emphasizing human augmentation, with specific examples of how AI supports work | DF5: A clear, accessible channel shows which AI projects are in scope, in pilot, in production, and why, with regular updates | DG5: AI rollouts include WIIFM messaging that identifies specific pain points and estimated personal benefits for the target role | DH5: Enterprise and local leadership share consistent AI messaging supported by cascaded talking points | DI5: A documented AI champion network covers all major business units, with defined responsibilities and recognition | DJ5: Senior executives visibly use AI tools and share examples of their own usage with the workforce | DK5: Resistance is mapped by function and role, with documented engagement plans for high-resistance segments | DL5: A documented, blame-free feedback channel allows users to report AI tool issues, with a defined triage process | DM5: A formal AI literacy audit identifies the gap between current workforce skills and the AI roadmap's requirements | DN5: Each major function has tailored AI adoption training (AI for HR, Finance, Sales, Operations, etc.) | DO5: Employees are given protected time for AI learning and experimentation, supported by a documented policy | DP5: An AI help desk and knowledge base offer use-case prompts, troubleshooting, and AI-specific support | DQ5: Adoption is measured via active users, task completion, and at least one business-outcome metric for each major AI tool | DR5: Performance reviews include criteria recognizing safe, innovative AI use, and managers are guided to apply them consistently | DS5: Shadow AI discovery triggers a documented "understand-and-govern" workflow that triages risk, brings tools into the inventory, and offers approved alternatives | DT5: A defined post-implementation review (e.g., at six months) confirms whether the business process changed and surfaces reversion | DU5: A standardized AI hosting strategy defines approved platforms and consistent security controls across the AI portfolio | DV5: A centralized, governed vector database is the default for RAG use cases, with documented access and ingestion patterns | DW5: The architecture supports elastic AI compute with isolation from core business systems and documented capacity planning | DX5: The architecture supports agentic patterns with documented standards for tool registration, agent governance, and observability | DY5: A central model registry holds every approved model version, with required metadata (owner, intended use, risk tier) | DZ5: All AI model calls route through a centralized gateway that handles authentication, safety filtering, cost attribution, and observability | EA5: A documented BYOM process vets open-source models for license, security, performance, and intended use before onboarding | EB5: AI deployment pipelines include continuous monitoring with defined metrics, alerts, and ownership | EC5: RAG and AI outputs include traceable lineage back to source documents or data records | ED5: The architecture supports real-time data streaming to AI workloads for use cases that require it | EE5: A common metadata schema enables AI models to consistently identify, share, and interpret data assets | EF5: A documented middle layer detects and masks PII/PHI before sending data to AI models | EG5: Automated tooling scans AI endpoints for prompt injection, jailbreak attempts, and adversarial inputs on a defined cadence | EH5: The architecture supports AI cost attribution by department, project, or use case, used for internal rebilling and value tracking | EI5: AI interaction logs are stored with defined retention and immutability suitable for compliance and legal discovery | EJ5: A model abstraction layer or gateway enables switching between providers with limited application impact | EK5: Every production AI model has a single named individual accountable for ethical and legal compliance | EL5: The AI Council is explicitly Accountable for the AI governance framework, with documented decision rights | EM5: The RACI explicitly requires Legal and Privacy consultation before production deployment, with documented sign-offs | EN5: Run-cost accountability is defined in the RACI and assigned to the business unit (or shared) as part of the transition to production | EO5: The RACI defines clear Responsible and Accountable parties for verifying training data lineage and right to use | EP5: The RACI assigns Responsibility for model selection (typically Architecture or a CoE) within enterprise standards, with Accountability defined | EQ5: The RACI defines joint Responsibility (IT + Business SME) for prompts and guardrails, with clear Accountability | ER5: The RACI defines a clear Responsible party for go-live decisions, with defined gate criteria (bias, safety, performance) | ES5: The RACI assigns clear Responsibility for production monitoring (typically MLOps/Engineering) with defined SLAs | ET5: The RACI defines a clear Accountable party for AI incident remediation and customer/regulator communication | EU5: The RACI clearly marks human reviewers as Responsible for the final output in HITL use cases | EV5: The RACI assigns Responsibility for decommissioning decisions with defined staleness criteria | EW5: Executive leaders are informed of AI deployments at a cadence and depth tied to risk tier (e.g., immediate for high-risk, periodic for low-risk) | EX5: The RACI assigns clear Responsibility for AI disclosure to end users, with required language or notice formats | EY5: The RACI defines who is Informed and Responsible for vendor model changes, with a documented process for evaluating impact
A6: A named executive owns AI accountability and is supported by formal governance, KPIs, risk oversight, and enterprise-wide operating model integration | B6: The governance body is fully cross-functional, has formal authority, includes technical and non-technical stakeholders, and regularly adjusts membership based on AI portfolio needs | C6: The council has formal decision rights, escalation authority, auditability, and enforcement mechanisms integrated into funding, delivery, and production release processes | D6: The council has a structured cadence, rapid review paths for lower-risk use cases, escalation paths for high-risk use cases, and regularly adjusts cadence based on portfolio demand | E6: Escalation paths, decision rights, risk ownership, audit trails, and executive tie-breaking authority are formally embedded into the AI governance process | F6: AI risk tiering is standardized, documented, auditable, aligned to regulatory frameworks, and integrated into intake, delivery, vendor review, monitoring, and production release processes | G6: Responsible AI standards are measurable, auditable, embedded into delivery and monitoring processes, and tailored by use case risk level and regulatory context | H6: Shadow AI is actively managed through policy, training, approved enterprise tools, monitoring, exception handling, and periodic compliance review | I6: AI documentation is standardized, reviewed, version-controlled, auditable, tied to risk tiering, and maintained throughout the solution lifecycle | J6: Regulatory and standards alignment is actively maintained, audited, assigned to control owners, and integrated into governance, risk tiering, vendor review, and delivery processes | K6: The AI inventory is authoritative, integrated with procurement, risk tiering, monitoring, and the change management process, and is reviewed on a defined cadence | L6: Vendor AI risk is continuously managed through risk-tiered procurement, contractual controls, ongoing attestation, monitoring of vendor model changes, and integration with the AI inventory | M6: Monitoring is risk-tiered, automated, integrated with retraining and incident response, includes drift and fairness signals, and feeds continuous improvement of the AI portfolio | N6: AI incident response is rehearsed, integrated with enterprise incident management, supported by automated kill-switch capability, and continuously improved through lessons learned | O6: Governance funding is risk-tiered, performance-measured, integrated into the enterprise AI operating model, and adjusted on a defined cadence based on portfolio growth and regulatory change | P6: Executive AI literacy is structured, refreshed regularly, tailored to changing capabilities (e.g., generative AI, agentic AI), and embedded into governance, audit, and strategy reviews | Q6: Governance and Responsible AI outcomes are embedded into performance management, leadership reviews, incentive design, and recognition programs across delivery, business, and executive levels | R6: AI speak-up channels are actively promoted, integrated with governance and incident response, anonymous, monitored for retaliation risk, and feed continuous improvement of AI policies | S6: AI value cases are standardized, baselined, tracked post-deployment, reviewed by governance, and feed portfolio prioritization and funding decisions | T6: Sourcing decisions are governed, regularly refreshed, integrated with portfolio strategy and architecture standards, and supported by reusable patterns and total-cost modeling | U6: AI investments are continuously evaluated against competitive intelligence, customer signals, and unique data assets, and the portfolio is actively rebalanced to defend strategic moats | V6: The internal-versus-external mix is actively governed, linked to strategic priorities, adjusted based on value realization, and informs funding and resource allocation | W6: Data readiness is treated as a first-class investment stream, linked to AI portfolio value, tracked against KPIs, and continuously prioritized with the AI roadmap | X6: The horizon balance is reviewed regularly, adjusted based on value realized and organizational readiness, and used to set funding, hiring, and communication priorities | Y6: Dependencies are continuously maintained, integrated with architecture standards, used to drive platform investment, and reviewed during portfolio governance | Z6: Roadmap refresh is continuous, evidence-driven, integrated with value tracking and governance reviews, and supported by an explicit culture of stopping work that is no longer valuable | AA6: AI talent is treated as a strategic asset, with continuous workforce planning, role evolution as AI capabilities change, and a balanced internal/external model | AB6: AI run costs are continuously monitored, attributed to business outcomes, optimized through architecture and model selection, and integrated with FinOps practices | AC6: SME engagement is a managed capacity discipline, included in portfolio planning, supported by tooling for labeling and validation, and refreshed as AI use cases evolve | AD6: Workforce enablement is continuous, role-specific, tied to adoption KPIs, integrated with HR and learning systems, and adjusted as the AI portfolio evolves | AE6: Success criteria are standardized, multi-dimensional (technical, adoption, value, responsibility), tracked post-deployment, and feed continuous portfolio decisions | AF6: Time-to-value expectations are tiered by initiative type, embedded in stage-gates, reviewed against actuals, and used to refresh portfolio strategy | AG6: Attribution is standardized, peer-reviewed, integrated with experimentation infrastructure, and used to refine future investment decisions and portfolio prioritization | AH6: Fairness definitions are standardized by use case type, embedded in delivery and review processes, auditable, and revisited as regulations and norms evolve | AI6: Representativeness analysis is standardized, risk-tiered, integrated with model documentation, repeated when data is refreshed, and informs data acquisition strategy | AJ6: Bias auditing is risk-tiered, automated where possible, integrated with monitoring and retraining, and tracked through governance reporting | AK6: Bias remediation is rehearsed, integrated with monitoring and incident response, supported by tooling for rapid retraining or rollback, and continuously improved through lessons learned | AL6: Transparency documentation is standardized, version-controlled, accessible to relevant users and reviewers, and kept current through automated workflows tied to model changes | AM6: Explainability is risk-tiered, embedded in customer-facing systems, supported by explainability tooling, tested for clarity, and improved through user feedback | AN6: The appeal process is risk-tiered by use case impact, staffed appropriately, tracked against SLAs, audited for fairness, and used as input to model improvement | AO6: Vendor explainability requirements are risk-tiered, contractually enforceable, validated through demonstrations or audits, and refreshed as vendor models are updated | AP6: Red-teaming is integrated into the AI development lifecycle, risk-tiered, supplemented by external testing where appropriate, and feeds continuous improvement of safety controls | AQ6: Drift detection is risk-tiered, multi-signal (data, performance, fairness), integrated with retraining and incident response, and continuously refined based on observed patterns | AR6: AI security is risk-tiered, continuously tested (including red-teaming), integrated with enterprise security operations, and refreshed as new AI threats emerge | AS6: Kill-switch capability is tested, automated where appropriate, integrated with incident response, and audited for response-time SLAs | AT6: Accountable ownership is tracked centrally, reviewed at handoffs, integrated with performance management, and supported by training for accountable owners | AU6: Data minimization is standardized, auditable, integrated with privacy reviews and data lineage tooling, and revisited as models and data sources evolve | AV6: Consent alignment is tracked through data lineage tooling, audited regularly, integrated with privacy operations, and refreshed when terms of service or regulations change | AW6: AI sustainability is reported externally where required, integrated with enterprise ESG reporting, influences architecture and vendor decisions, and is tracked against improvement targets | AX6: ROI is standardized, validated post-deployment against forecast, integrated with portfolio governance, and refreshed as cost and value assumptions change | AY6: Time-to-value is tracked, trended, benchmarked, integrated with portfolio governance, and used to identify and remove systemic delivery bottlenecks | AZ6: Productivity gains are measured continuously, validated through sampling, tied to business outcomes, and used to inform AI investment, role design, and operating model evolution | BA6: Experience metrics are integrated with AI portfolio governance, used to inform model improvements, and reported alongside financial value | BB6: Ground-truth practice is standardized, version-controlled, refreshed on a defined cadence, integrated with monitoring, and supports both internal and vendor model evaluations | BC6: AI performance SLAs are risk-tiered, integrated with capacity planning and cost optimization, continuously trended, and adjusted based on user experience data | BD6: Hallucination and groundedness are continuously measured, tied to grounding architecture (e.g., RAG quality), trended, and used to drive prompt, retrieval, and model improvements | BE6: Drift measurement is risk-tiered, automated, integrated with MLOps/LLMOps pipelines, validated against business outcomes, and feeds continuous model improvement | BF6: Unit-cost visibility is integrated with FinOps, attributed to business outcomes, optimized through model and architecture choices, and reviewed at portfolio governance | BG6: Utilization optimization is automated where appropriate, integrated with FinOps, tied to performance SLAs and sustainability targets, and continuously improved | BH6: TCO is standardized, validated against actuals, integrated with portfolio governance, and used to inform sourcing, sequencing, and value decisions | BI6: Sustainability metrics are integrated with architecture choices, model selection, vendor evaluation, and enterprise ESG reporting | BJ6: Fairness reporting is standardized, risk-tiered, drives documented remediation, integrated with model lifecycle and external reporting where required | BK6: Agreement-rate analysis is standardized, integrated with monitoring and retraining, used to refine model design and human-AI workflow, and reported through governance | BL6: Audit readiness is automated through model registry and monitoring tooling, with retention policies aligned to regulatory requirements and rehearsed audit procedures | BM6: Coverage measurement is automated through the model registry, tied to release gates, reported to governance, and integrated with audit readiness | BN6: The operating model is governed, periodically reviewed, integrated with talent and funding decisions, and adjusted as the AI portfolio and organizational strategy evolve | BO6: Dual ownership is standardized, supported by training and onboarding, integrated with performance management, and refreshed as initiatives evolve | BP6: Shadow AI discovery is continuous, automated where possible, integrated with the AI inventory and procurement, and supported by an amnesty / onboarding workflow that encourages disclosure | BQ6: The funding model is reviewed annually, balanced with portfolio strategy, integrated with FinOps and value tracking, and adjusted as AI demand and value evolve | BR6: Intake is risk-tiered, supported by tooling, integrated with portfolio prioritization and funding, and continuously refined based on throughput and outcome data | BS6: HITL is risk-tiered, integrated into delivery and monitoring, evaluated through agreement-rate metrics, and continuously improved based on outcomes | BT6: Decommissioning is risk-tiered, integrated with monitoring and audit, automated where possible, and supports clean rollback and replacement | BU6: RACI is rehearsed through tabletop exercises, embedded in onboarding, validated through incident reviews, and refreshed when roles change | BV6: The data supply chain is governed, monitored for quality and freshness, integrated with data governance and observability, and continuously expanded based on AI demand | BW6: The inventory dashboard is automated, integrated with monitoring, vendor AI capabilities, and governance reporting, and feeds risk and value decisions in real time | BX6: Tooling standards are reviewed regularly, balance enterprise consistency with innovation, integrated with architecture review and procurement, and support deprecation pathways | BY6: Guardrails are risk-tiered, continuously updated, tracked through quality metrics, integrated with monitoring, and feed back into model improvements | BZ6: AI role definitions are reviewed as the operating model evolves, integrated with HR systems, supported by career pathing, and aligned to workforce planning | CA6: KPIs are reviewed regularly, tied to incentives and performance management, supported by training, and adjusted as the operating model evolves | CB6: Non-technical AI literacy is refreshed as capabilities evolve, integrated with HR and compliance systems, measured for impact on decision quality, and supported by office hours or expert access | CC6: Scoring is calibrated through periodic exercises, integrated with portfolio governance, validated against post-deployment outcomes, and refined over time | CD6: Value definition is reviewed against strategic priorities, refreshed annually, validated post-deployment, and used to inform funding decisions | CE6: Feasibility assessment is calibrated against actual delivery effort, supported by reference patterns, and integrated with architecture and data readiness reviews | CF6: The right-tool review is supported by reference patterns, integrated with architecture and automation pipelines, and measured for accuracy against post-deployment outcomes | CG6: Strategic alignment is reviewed annually, updated as priorities shift, validated through portfolio outcomes, and shapes both funding and resource allocation | CH6: Horizon mix is governed, supported by separate funding for Horizon 2/3 bets, evaluated on appropriate timelines, and adjusted as portfolio outcomes mature | CI6: Active rebalancing is a normal portfolio discipline, supported by transparent kill criteria, executive sponsorship, and lessons-learned capture | CJ6: Resource allocation is governed, supported by capacity planning data, integrated with talent strategy, and validated through portfolio throughput metrics | CK6: Pre-prioritization risk screening is risk-tiered, supported by tooling, integrated with downstream governance reviews, and continuously improved based on outcomes | CL6: Governance cost estimates are calibrated against actuals, risk-tiered, integrated with TCO modeling, and refined as governance practices evolve | CM6: Sovereignty and vendor risk scoring is integrated with vendor risk management, contract review, architecture standards, and is refreshed as regulations change | CN6: Champion commitment is reviewed at intake, supported by training, tracked against adoption KPIs, and reinforced through performance management | CO6: Change management scoring is calibrated against post-deployment adoption outcomes, integrated with the change plan, and refined over time | CP6: The failed-use-case learning loop is supported by a queryable repository, integrated with intake and scoring, and contributes to evolving the prioritization rubric | CQ6: Fluency is assessed, refreshed as capabilities evolve, validated through scenario exercises, and reinforced through periodic briefings | CR6: Regulatory training is refreshed as laws evolve, supported by external expert briefings, and applied in scenario-based decision exercises | CS6: Calibration is run on a defined cadence, measured for inter-rater agreement, refreshed with new scenarios as AI capabilities evolve, and used to refine risk rubrics | CT6: Explainability inquiry skills are refreshed as model types evolve, supported by reference questions per use-case type, and integrated into risk review templates | CU6: Failure-mode literacy is refreshed as AI capabilities evolve, supported by reference report templates, and reinforced through case studies | CV6: Tool-awareness training is refreshed when the approved list changes, measured for retention, and reinforced through ongoing communications and just-in-time prompts | CW6: Training is role-specific, supported by reference patterns ("Golden Prompts" and verification checklists), and refreshed as AI capabilities and risks evolve | CX6: Training is role-specific, integrated with data classification systems, supported by just-in-time guidance in AI tools, and reinforced through audits | CY6: Accountability messaging is embedded in AI tools, reinforced through periodic training, supported by examples of misuse, and reflected in performance management | CZ6: Use case recognition is supported by reference patterns, integrated with intake tooling, refreshed as AI capabilities expand, and tracked through intake quality metrics | DA6: Persona paths are reviewed for relevance, supported by certifications, integrated with the operating model, and refreshed as roles evolve | DB6: Refresh is event-driven (responding to new AI capabilities and regulations), supported by content version control, and tracked through learner re-engagement | DC6: Behavior-change measurement is integrated with the training program, reviewed regularly, used to refine content, and reported alongside training KPIs | DD6: Access is integrated with AI tools (in-product help), supported by SLA, measured for use and outcomes, and continuously improved based on common question patterns | DE6: The vision is reinforced through ongoing communications, examples, and senior leader behavior; messaging is validated through workforce sentiment data and refined | DF6: Portfolio transparency is supported by an interactive dashboard, two-way communication, integrated with governance reporting, and refreshed in near real time | DG6: WIIFM messaging is validated against actual user experience, refined over time, integrated with training, and tied to adoption metrics | DH6: Cascade messaging is supported by leader briefings, monitored through sentiment data, refreshed regularly, and reinforced through leader performance management | DI6: The champion network is actively managed, regularly trained, supported by tooling and recognition, measured through adoption impact, and refreshed as the AI portfolio expands | DJ6: Executive AI use is normalized, modeled in leader communications, supported by executive AI training, and measured as part of digital leadership expectations | DK6: Resistance mapping is refreshed, engagement plans are tracked for impact, integrated with HR and leadership planning, and informed by sentiment monitoring | DL6: Feedback is integrated with monitoring, used to drive model and tool improvements, anonymized where appropriate, and reported on for trust transparency | DM6: Literacy audits are refreshed on a defined cadence, integrated with workforce planning, used to drive training and hiring, and tracked over time | DN6: Function-specific training is refreshed as use cases evolve, integrated with function-level adoption goals, and measured against function-level outcomes | DO6: Protected learning time is integrated with adoption KPIs, supported by tooling and content, measured for use, and adjusted as AI roles evolve | DP6: Support resources are continuously updated, integrated with AI tools (in-product help), measured for use and satisfaction, and refined based on common queries | DQ6: Adoption KPIs are integrated with portfolio governance, reviewed by leadership, used to drive iteration of tools and training, and aligned with value realization | DR6: AI-aware performance management is supported by HR systems, validated through outcomes, refreshed as practices evolve, and reinforced through visible recognition | DS6: Shadow AI response is risk-tiered, supports an amnesty / onboarding program, integrated with discovery tooling, and used as a signal of unmet workforce demand | DT6: Post-launch reviews are standardized, integrated with portfolio governance and value tracking, and drive remediation, re-training, or process redesign when adoption falls short | DU6: Hosting strategy is reviewed regularly, integrated with security and FinOps, supports use-case-appropriate placement (cloud / hybrid / on-prem), and balances innovation with control | DV6: Vector infrastructure is integrated with data governance, observability, and access controls, with re-use metrics, performance tuning, and lifecycle management | DW6: Elasticity is supported by autoscaling, traffic management, SLA monitoring, FinOps integration, and capacity forecasting for emerging AI workloads | DX6: Agentic AI is supported by a governed agent platform with risk-tiered tool allow-lists, integrated security and audit, and continuous evaluation of agent behavior | DY6: The registry is integrated with CI/CD, monitoring, governance, and audit workflows; access is governed and changes are tracked | DZ6: The LLM gateway is feature-rich (multi-provider routing, prompt and output filtering, cost optimization, A/B testing), integrated with governance, and continuously improved | EA6: BYOM is risk-tiered, supported by an internal model catalog, integrated with security and procurement, and refreshed as new open-source models emerge | EB6: Continuous monitoring is risk-tiered, automated where possible, integrated with retraining workflows and incident response, and supports proactive remediation | EC6: AI lineage is automated, integrated with data governance and audit, supports user-visible citations, and is refreshed as sources change | ED6: Real-time access is integrated with data governance, observability, and quality monitoring; latency SLAs are met and continuously optimized | EE6: Metadata is governed, automated, integrated with the data catalog and AI tooling, refreshed as schemas evolve, and powers semantic search and AI discovery | EF6: Sanitization is risk-tiered, integrated with the LLM gateway and data catalog, monitored for accuracy, and continuously improved through false-positive/negative analysis | EG6: Automated AI security testing is integrated with CI/CD and runtime monitoring, supports continuous scanning, generates remediation tickets, and is refreshed with new attack patterns | EH6: Cost attribution is integrated with FinOps, automated, used to drive optimization and value-tracking decisions, and refreshed as new AI services are added | EI6: Audit logs are risk-tiered, integrated with SIEM, support fast retrieval for audit and discovery, validated through retention drills, and aligned with regulatory requirements | EJ6: Provider portability is tested through periodic model-swap exercises, integrated with evaluation tooling, and informs procurement and architecture decisions | EK6: Accountable owners are governed centrally, supported by training and tooling, validated at handoffs, and integrated with performance management | EL6: Framework accountability is reviewed annually, supported by performance metrics on framework health, and integrated with strategic and audit reporting | EM6: Pre-production review is risk-tiered, supported by tooling and SLA, integrated with deployment automation, and validated through audit | EN6: Run-cost accountability is integrated with FinOps, value tracking, and optimization workflows, and is reviewed as part of portfolio governance | EO6: Provenance verification is integrated with the data catalog and AI delivery pipeline, supported by automation, and validated through audits | EP6: Model selection is governed, supported by reference patterns and a model catalog, tracked through architecture review, and revisited as new models emerge | EQ6: Prompt and guardrail ownership is supported by versioning, testing, evaluation, and governance review, and continuously improved through monitoring | ER6: Go-live authority is risk-tiered, supported by automated gate checks, audited for consistency, and refreshed as gate criteria evolve | ES6: Monitoring responsibility is risk-tiered, integrated with on-call processes and incident response, and supports automated remediation where appropriate | ET6: Incident accountability is rehearsed through tabletop exercises, integrated with enterprise incident management, supported by playbooks, and continuously improved through lessons learned | EU6: Reviewer role is reinforced through training, supported by reviewer agreement metrics, integrated with feedback into model improvements, and audited for quality | EV6: Decommissioning authority is integrated with monitoring signals, supported by tooling, reviewed through portfolio governance, and validated through audits | EW6: Executive communication is integrated with governance reporting, supports board-level oversight where appropriate, and is refreshed as risk tiers and regulatory expectations change | EX6: Disclosure is risk-tiered, integrated with AI tools and customer-facing systems, validated through audit, and aligned with applicable regulations | EY6: Vendor change awareness is automated, integrated with regression testing, supports rapid response to breaking changes, and feeds vendor risk management
A7: Not sure | B7: Not sure | C7: Not sure | D7: Not sure | E7: Not sure | F7: Not sure | G7: Not sure | H7: Not sure | I7: Not sure | J7: Not sure | K7: Not sure | L7: Not sure | M7: Not sure | N7: Not sure | O7: Not sure | P7: Not sure | Q7: Not sure | R7: Not sure | S7: Not sure | T7: Not sure | U7: Not sure | V7: Not sure | W7: Not sure | X7: Not sure | Y7: Not sure | Z7: Not sure | AA7: Not sure | AB7: Not sure | AC7: Not sure | AD7: Not sure | AE7: Not sure | AF7: Not sure | AG7: Not sure | AH7: Not sure | AI7: Not sure | AJ7: Not sure | AK7: Not sure | AL7: Not sure | AM7: Not sure | AN7: Not sure | AO7: Not sure | AP7: Not sure | AQ7: Not sure | AR7: Not sure | AS7: Not sure | AT7: Not sure | AU7: Not sure | AV7: Not sure | AW7: Not sure | AX7: Not sure | AY7: Not sure | AZ7: Not sure | BA7: Not sure | BB7: Not sure | BC7: Not sure | BD7: Not sure | BE7: Not sure | BF7: Not sure | BG7: Not sure | BH7: Not sure | BI7: Not sure | BJ7: Not sure | BK7: Not sure | BL7: Not sure | BM7: Not sure | BN7: Not sure | BO7: Not sure | BP7: Not sure | BQ7: Not sure | BR7: Not sure | BS7: Not sure | BT7: Not sure | BU7: Not sure | BV7: Not sure | BW7: Not sure | BX7: Not sure | BY7: Not sure | BZ7: Not sure | CA7: Not sure | CB7: Not sure | CC7: Not sure | CD7: Not sure | CE7: Not sure | CF7: Not sure | CG7: Not sure | CH7: Not sure | CI7: Not sure | CJ7: Not sure | CK7: Not sure | CL7: Not sure | CM7: Not sure | CN7: Not sure | CO7: Not sure | CP7: Not sure | CQ7: Not sure | CR7: Not sure | CS7: Not sure | CT7: Not sure | CU7: Not sure | CV7: Not sure | CW7: Not sure | CX7: Not sure | CY7: Not sure | CZ7: Not sure | DA7: Not sure | DB7: Not sure | DC7: Not sure | DD7: Not sure | DE7: Not sure | DF7: Not sure | DG7: Not sure | DH7: Not sure | DI7: Not sure | DJ7: Not sure | DK7: Not sure | DL7: Not sure | DM7: Not sure | DN7: Not sure | DO7: Not sure | DP7: Not sure | DQ7: Not sure | DR7: Not sure | DS7: Not sure | DT7: Not sure | DU7: Not sure | DV7: Not sure | DW7: Not sure | DX7: Not sure | DY7: Not sure | DZ7: Not sure | EA7: Not sure | EB7: Not sure | EC7: Not sure | ED7: Not sure | EE7: Not sure | EF7: Not sure | EG7: Not sure | EH7: Not sure | EI7: Not sure | EJ7: Not sure | EK7: Not sure | EL7: Not sure | EM7: Not sure | EN7: Not sure | EO7: Not sure | EP7: Not sure | EQ7: Not sure | ER7: Not sure | ES7: Not sure | ET7: Not sure | EU7: Not sure | EV7: Not sure | EW7: Not sure | EX7: Not sure | EY7: Not sure
A8: Not applicable | B8: Not applicable | C8: Not applicable | D8: Not applicable | E8: Not applicable | F8: Not applicable | G8: Not applicable | H8: Not applicable | I8: Not applicable | J8: Not applicable | K8: Not applicable | L8: Not applicable | M8: Not applicable | N8: Not applicable | O8: Not applicable | P8: Not applicable | Q8: Not applicable | R8: Not applicable | S8: Not applicable | T8: Not applicable | U8: Not applicable | V8: Not applicable | W8: Not applicable | X8: Not applicable | Y8: Not applicable | Z8: Not applicable | AA8: Not applicable | AB8: Not applicable | AC8: Not applicable | AD8: Not applicable | AE8: Not applicable | AF8: Not applicable | AG8: Not applicable | AH8: Not applicable | AI8: Not applicable | AJ8: Not applicable | AK8: Not applicable | AL8: Not applicable | AM8: Not applicable | AN8: Not applicable | AO8: Not applicable | AP8: Not applicable | AQ8: Not applicable | AR8: Not applicable | AS8: Not applicable | AT8: Not applicable | AU8: Not applicable | AV8: Not applicable | AW8: Not applicable | AX8: Not applicable | AY8: Not applicable | AZ8: Not applicable | BA8: Not applicable | BB8: Not applicable | BC8: Not applicable | BD8: Not applicable | BE8: Not applicable | BF8: Not applicable | BG8: Not applicable | BH8: Not applicable | BI8: Not applicable | BJ8: Not applicable | BK8: Not applicable | BL8: Not applicable | BM8: Not applicable | BN8: Not applicable | BO8: Not applicable | BP8: Not applicable | BQ8: Not applicable | BR8: Not applicable | BS8: Not applicable | BT8: Not applicable | BU8: Not applicable | BV8: Not applicable | BW8: Not applicable | BX8: Not applicable | BY8: Not applicable | BZ8: Not applicable | CA8: Not applicable | CB8: Not applicable | CC8: Not applicable | CD8: Not applicable | CE8: Not applicable | CF8: Not applicable | CG8: Not applicable | CH8: Not applicable | CI8: Not applicable | CJ8: Not applicable | CK8: Not applicable | CL8: Not applicable | CM8: Not applicable | CN8: Not applicable | CO8: Not applicable | CP8: Not applicable | CQ8: Not applicable | CR8: Not applicable | CS8: Not applicable | CT8: Not applicable | CU8: Not applicable | CV8: Not applicable | CW8: Not applicable | CX8: Not applicable | CY8: Not applicable | CZ8: Not applicable | DA8: Not applicable | DB8: Not applicable | DC8: Not applicable | DD8: Not applicable | DE8: Not applicable | DF8: Not applicable | DG8: Not applicable | DH8: Not applicable | DI8: Not applicable | DJ8: Not applicable | DK8: Not applicable | DL8: Not applicable | DM8: Not applicable | DN8: Not applicable | DO8: Not applicable | DP8: Not applicable | DQ8: Not applicable | DR8: Not applicable | DS8: Not applicable | DT8: Not applicable | DU8: Not applicable | DV8: Not applicable | DW8: Not applicable | DX8: Not applicable | DY8: Not applicable | DZ8: Not applicable | EA8: Not applicable | EB8: Not applicable | EC8: Not applicable | ED8: Not applicable | EE8: Not applicable | EF8: Not applicable | EG8: Not applicable | EH8: Not applicable | EI8: Not applicable | EJ8: Not applicable | EK8: Not applicable | EL8: Not applicable | EM8: Not applicable | EN8: Not applicable | EO8: Not applicable | EP8: Not applicable | EQ8: Not applicable | ER8: Not applicable | ES8: Not applicable | ET8: Not applicable | EU8: Not applicable | EV8: Not applicable | EW8: Not applicable | EX8: Not applicable | EY8: Not applicable
